<?xml version="1.0" encoding="UTF-8" standalone="yes"?>
<?xml-stylesheet type="text/xsl" href="fullText.xsl"?>
<fullTextAnnotation xmlns="http://framenet.icsi.berkeley.edu" xmlns:xsi="http://www.w3.org/2001/XMLSchema-instance" xsi:schemaLocation="../schema/fullText.xsd">
    <header>
        <corpus description="LSI" name="LSI" ID="1">
            <document description="lsi_vol3_p3_tibeto-burman_langrong" name="lsi_vol3_p3_tibeto-burman_langrong" ID="42"/>
        </corpus>
    </header>
<sentence ID="16581"><text>LANGRONG .</text></sentence><sentence ID="16582"><text>The Langrongs , according to Mr.Soppitt , are the Kukis inhabiting the Tipperah Hills , and are identical with the Rāngkhōlṣ The specimens and the list of standard words and phrases which are given below have been forwarded as specimens in Kuki .</text></sentence><sentence ID="16583"><text>Their language is so closely related to Rāngkhōl and Hallām that I do not hesitate to identify it with the Langrong mentioned by Mr.Soppitt .</text><annotationSet ID="25234" luID="28360" luName="language.n" frameID="1249" frameName="linguistic_system"><layer name="fe"><label ID="11628" name="language_family" start="40" end="47"/><label ID="11628" name="language_family" start="53" end="58"/><label ID="11634" name="spoken_by" start="132" end="138"/><label ID="11629" name="language_group" start="107" end="114"/></layer><layer name="target"><label ID="1" name="Target" start="6" end="13"/></layer></annotationSet></sentence><sentence ID="16584"><text>Langrong or Lengreng is also spoken by a few individuals in the Cachar Plains , to the south and east of the Sadr Sub-division .</text></sentence><sentence ID="16585"><text>They have come down from the hills since the Census of 1891 .</text></sentence><sentence ID="16586"><text>The Deputy Commissioner gives 399 as the total for Rāltē , Saimar and Lengreng , without saying how many speakers there are of each .</text></sentence><sentence ID="16587"><text>It has proved impossible to get any specimens .</text></sentence><sentence ID="16588"><text>Mr.Damant called the tribe Ranglong and found it in North Cachar .</text></sentence><sentence ID="16589"><text>In Sylhet there are said to be 1,600 speakers of Kuki .</text></sentence><sentence ID="16590"><text>No specimens have been received , but the numerals have been taken down in several parts of the district , and in two cases , they agree with the forms given in the Tipperah list , while two other lists apparently belong to Hallām and Thādo respectively .</text><annotationSet ID="27115" luID="28306" luName="numeral.n" frameID="1232" frameName="numeral"><layer name="target"><label ID="1" name="Target" start="42" end="49"/></layer></annotationSet><annotationSet ID="27116" luID="28290" luName="agree.v" frameID="1226" frameName="agreement"><layer name="fe"><label ID="11499" name="participant_2" start="137" end="177"/><label ID="11498" name="participant_1" start="126" end="129"/></layer><layer name="target"><label ID="1" name="Target" start="131" end="135"/></layer></annotationSet></sentence><sentence ID="16591"><text>We may provisionally put down 533 as the total for Langrong in Sylhet and 133 in the Cachar Plains .</text></sentence><sentence ID="16592"><text>If we suppose that the 5,600 individuals who are returned as speaking Kuki in Hill Tipperah speak Langrong , the probable totals for this dialect would be : AUTHORITIES Smart , Robert B ., Geographical and Statistical Report on the District of Tipperah .</text></sentence><sentence ID="16593"><text>Calcutta , 1866 .</text></sentence><sentence ID="16594"><text>Tipperah ( i.e., Langrong ) vocabulary on p .3 .</text></sentence><sentence ID="16595"><text>Campbell , Sir George , Specimens of Languages of India , including those of the Aboriginal Tribes of Bengal , the Central Provinces and the Eastern Frontier .</text><annotationSet ID="26016" luID="28360" luName="language.n" frameID="1249" frameName="linguistic_system"><layer name="fe"><label ID="11633" name="location" start="50" end="54"/><label ID="11633" name="location" start="102" end="107"/><label ID="11633" name="location" start="115" end="121"/><label ID="11633" name="location" start="123" end="131"/><label ID="11633" name="location" start="141" end="147"/><label ID="11633" name="location" start="149" end="156"/></layer><layer name="target"><label ID="1" name="Target" start="37" end="45"/></layer></annotationSet></sentence><sentence ID="16596"><text>Calcutta , 1874 .</text></sentence><sentence ID="16597"><text>Kukee of Tipperah on pp .</text></sentence><sentence ID="16598"><text>204 and ff.</text></sentence><sentence ID="16599"><text>; probably also the ‘ Kuki ’ specimens on pp .</text></sentence><sentence ID="16600"><text>220 and ff.</text></sentence><sentence ID="16601"><text>Soppitt , C .A ., A Short Account of the Kuki Lushai Tribes on the North-East Frontier ( Districts Cachar , Sylhet , Năga Hills , etc., and the North Cachar Hills ) , with an Outline Grammar of the Rangkhol-Lushai Language and A Comparison of Lushai with other Dialects .</text><annotationSet ID="26017" luID="28361" luName="grammar.n" frameID="1249" frameName="linguistic_system"><layer name="fe"><label ID="11630" name="language" start="198" end="205"/><label ID="11630" name="language" start="207" end="212"/><label ID="11627" name="language_subfamily" start="243" end="248"/></layer><layer name="target"><label ID="1" name="Target" start="183" end="189"/></layer></annotationSet><annotationSet ID="26018" luID="28360" luName="language.n" frameID="1249" frameName="linguistic_system"><layer name="fe"><label ID="11630" name="language" start="207" end="212"/><label ID="11630" name="language" start="198" end="205"/><label ID="11627" name="language_subfamily" start="243" end="248"/><label ID="11633" name="location" start="99" end="104"/><label ID="11633" name="location" start="108" end="113"/><label ID="11631" name="name" start="41" end="44"/><label ID="11631" name="name" start="46" end="51"/></layer><layer name="target"><label ID="1" name="Target" start="214" end="221"/></layer></annotationSet></sentence><sentence ID="16602"><text>Shillong , 1887 .</text></sentence><sentence ID="16603"><text>Mention of Langrong on p .3 .</text></sentence><sentence ID="16604"><text>Two specimens and a list of standard words and phrases have been received from Hill Tipperah .</text></sentence><sentence ID="16605"><text>The list seems to be corrupt .</text></sentence><sentence ID="16606"><text>It is , however , quite independent of the specimens and has therefore been useful for checking the results derived from the specimens .</text></sentence><sentence ID="16607"><text>The following remarks on Langrong , which are based on the materials just mentioned , are the first attempt to describe this language , and are given with every reserve .</text><annotationSet ID="26022" luID="28360" luName="language.n" frameID="1249" frameName="linguistic_system"><layer name="fe"><label ID="11630" name="language" start="25" end="32"/></layer><layer name="target"><label ID="1" name="Target" start="125" end="132"/></layer></annotationSet></sentence><sentence ID="16608"><text>Pronunciation .</text></sentence><sentence ID="16609"><text>The spelling in the list of words is very inconsistent .</text></sentence><sentence ID="16610"><text>I have corrected it as far as possible , but in some cases it is almost impossible to form an </text></sentence><sentence ID="16611"><text>accurate opinion of the pronunciation .</text></sentence><sentence ID="16612"><text>Thus , a^ and ō ; ai and ē , respectively , are used for the same sounds .</text></sentence><sentence ID="16613"><text>For instance , ra^ and rō , the suffix of the imperative ; tlai and ṭlē , to run ; pai , pē , and pēk , to give .</text><annotationSet ID="31045" luID="28389" luName="suffix.n" frameID="1258" frameName="affix"><layer name="fe"><label ID="11678" name="data" start="15" end="24"/><label ID="11677" name="subclass" start="39" end="55"/></layer><layer name="target"><label ID="1" name="Target" start="32" end="37"/></layer></annotationSet><annotationSet ID="31478" luID="28407" luName="imperative.n" frameID="1265" frameName="mood_property"><layer name="target"><label ID="1" name="Target" start="46" end="55"/></layer></annotationSet></sentence><sentence ID="16614"><text>The i of the suffix in may apparently be dropped after a preceding vowel ; thus , pā-in and pān , by the father .</text></sentence><sentence ID="16615"><text>The use of aspirated letters is rather inconsistent .</text></sentence><sentence ID="16616"><text>Thus , khāt and kāt , one ; phūng and pūng , stomach , etc.</text></sentence><sentence ID="16617"><text>Ph seems usually to be pronounced f ; thus , phāk or fāk , eat ; phēi or fēi , foot .</text></sentence><sentence ID="16618"><text>Dh and th are both written for d in the list , in the termination ding .</text></sentence><sentence ID="16619"><text>I have always written d , as do the specimens .</text></sentence><sentence ID="16620"><text>T.and t occur in the same word ; thus ṭlē or tlai , to run .</text></sentence><sentence ID="16621"><text>Consonants are occasionally silent ; thus , phāk and phā , to eat .</text><annotationSet ID="26032" luID="28282" luName="consonant.n" frameID="1225" frameName="form_unit"><layer name="fe"><label ID="11496" name="data" start="44" end="47"/><label ID="11496" name="data" start="53" end="55"/><label ID="11497" name="data_translation" start="59" end="64"/></layer><layer name="target"><label ID="1" name="Target" start="0" end="9"/></layer></annotationSet></sentence><sentence ID="16622"><text>We once find rēn-kā instead of rēng-kā , all , but the pronunciation is probably the same in both cases .</text></sentence><sentence ID="16623"><text>A euphonic y is sometimes written ; thus , nai-yā or nai-ā , under .</text></sentence><sentence ID="16624"><text>A consonant is sometimes doubled ; thus , allā or ālā , far ; ommā or a^m ā , being , etc.</text><annotationSet ID="26035" luID="28282" luName="consonant.n" frameID="1225" frameName="form_unit"><layer name="fe"><label ID="11496" name="data" start="42" end="45"/><label ID="11496" name="data" start="50" end="52"/><label ID="11497" name="data_translation" start="56" end="58"/><label ID="11496" name="data" start="62" end="65"/><label ID="11496" name="data" start="70" end="74"/><label ID="11497" name="data_translation" start="78" end="82"/></layer><layer name="target"><label ID="1" name="Target" start="2" end="10"/></layer></annotationSet></sentence><sentence ID="16625"><text>Articles .</text></sentence><sentence ID="16626"><text>The numeral khāt , one , is used as an indefinite article , and demonstrative pronouns or relative clauses supply the place of a definite article .</text><annotationSet ID="26036" luID="28306" luName="numeral.n" frameID="1232" frameName="numeral"><layer name="fe"><label ID="11529" name="data" start="12" end="15"/><label ID="11527" name="data_translation" start="19" end="21"/></layer><layer name="target"><label ID="1" name="Target" start="4" end="10"/></layer></annotationSet><annotationSet ID="26037" luID="28334" luName="pronoun.n" frameID="1243" frameName="pronominal"><layer name="fe"><label ID="11591" name="sublass" start="64" end="76"/></layer><layer name="target"><label ID="1" name="Target" start="78" end="85"/></layer></annotationSet><annotationSet ID="27442" luID="28340" luName="article.n" frameID="1245" frameName="article"><layer name="fe"><label ID="11600" name="subclass" start="129" end="136"/></layer><layer name="target"><label ID="1" name="Target" start="138" end="144"/></layer></annotationSet></sentence><sentence ID="16627"><text>Nouns .</text><annotationSet ID="26038" luID="28379" luName="noun.n" frameID="1255" frameName="noun"><layer name="target"><label ID="1" name="Target" start="0" end="4"/></layer></annotationSet></sentence><sentence ID="16628"><text>The word pā , father , occurs twice in the form kā-pā ; thus , kē kā-pā , my father , ā-ni kā-pā , his father .</text></sentence><sentence ID="16629"><text>But usually kē pā , ā pā .</text></sentence><sentence ID="16630"><text>Gender .</text><annotationSet ID="26040" luID="28364" luName="gender.n " frameID="1251" frameName="gender_property"><layer name="target"><label ID="1" name="Target" start="1" end="5"/></layer></annotationSet></sentence><sentence ID="16631"><text>Gender is only apparent in the case of animate beings .</text><annotationSet ID="26041" luID="28364" luName="gender.n " frameID="1251" frameName="gender_property"><layer name="target"><label ID="1" name="Target" start="1" end="5"/></layer></annotationSet></sentence><sentence ID="16632"><text>Different words may be used for the two sexes .</text></sentence><sentence ID="16633"><text>Thus pā , father ; nū , mother : pā-sāl , man ; nū-pāng , woman .</text></sentence><sentence ID="16634"><text>In other cases suffixes are used to denote the gender .</text><annotationSet ID="26044" luID="28389" luName="suffix.n" frameID="1258" frameName="affix"><layer name="fe"><label ID="11677" name="subclass" start="47" end="52"/></layer><layer name="target"><label ID="1" name="Target" start="15" end="22"/></layer></annotationSet><annotationSet ID="26045" luID="28364" luName="gender.n " frameID="1251" frameName="gender_property"><layer name="target"><label ID="1" name="Target" start="47" end="52"/></layer></annotationSet></sentence><sentence ID="16635"><text>Such are , in the case of human beings , pā , male ; nū , female .</text></sentence><sentence ID="16636"><text>In the case of animals the male suffix is chal , and the female pūi .</text><annotationSet ID="26048" luID="28389" luName="suffix.n" frameID="1258" frameName="affix"><layer name="fe"><label ID="11677" name="subclass" start="27" end="30"/><label ID="11678" name="data" start="42" end="45"/><label ID="11677" name="subclass" start="57" end="62"/><label ID="11678" name="data" start="64" end="66"/></layer><layer name="target"><label ID="1" name="Target" start="32" end="37"/></layer></annotationSet></sentence><sentence ID="16637"><text>Thus , nāi-pā , son ; nāi-nū , daughter : sā-kor chal , horse ; sā-kor pūi , mare .</text></sentence><sentence ID="16638"><text>Number .</text></sentence><sentence ID="16639"><text>The suffix of the plural is hēi ; thus , ṭēn-hēi , friends .</text><annotationSet ID="26466" luID="28389" luName="suffix.n" frameID="1258" frameName="affix"><layer name="fe"><label ID="11677" name="subclass" start="18" end="23"/><label ID="11678" name="data" start="28" end="30"/><label ID="11677" name="subclass" start="11" end="17"/></layer><layer name="target"><label ID="1" name="Target" start="4" end="9"/></layer></annotationSet></sentence><sentence ID="16640"><text>Case .</text></sentence><sentence ID="16641"><text>The Nominative , the Accusative , and the Dative do not take any suffix .</text><annotationSet ID="26469" luID="28389" luName="suffix.n" frameID="1258" frameName="affix"><layer name="fe"><label ID="11677" name="subclass" start="4" end="13"/><label ID="11677" name="subclass" start="21" end="30"/><label ID="11677" name="subclass" start="42" end="47"/></layer><layer name="target"><label ID="1" name="Target" start="65" end="70"/></layer></annotationSet><annotationSet ID="31046" luID="28414" luName="nominative.n" frameID="1266" frameName="case_property"><layer name="fe"><label ID="11707" name="sublass" start="4" end="13"/></layer><layer name="target"><label ID="1" name="Target" start="4" end="13"/></layer></annotationSet><annotationSet ID="31047" luID="28432" luName="accusative.n" frameID="1266" frameName="case_property"><layer name="fe"><label ID="11707" name="sublass" start="21" end="30"/></layer><layer name="target"><label ID="1" name="Target" start="21" end="30"/></layer></annotationSet><annotationSet ID="31048" luID="28410" luName="dative.n" frameID="1266" frameName="case_property"><layer name="fe"><label ID="11707" name="sublass" start="42" end="47"/></layer><layer name="target"><label ID="1" name="Target" start="42" end="47"/></layer></annotationSet></sentence><sentence ID="16642"><text>The subject of a transitive verb is usually distinguished by the suffix in , denoting the agent .</text><annotationSet ID="26470" luID="28337" luName="verb.n" frameID="1244" frameName="verbal"><layer name="fe"><label ID="11596" name="subclass" start="17" end="26"/></layer><layer name="target"><label ID="1" name="Target" start="28" end="31"/></layer></annotationSet></sentence><sentence ID="16643"><text>The verb may be a participle or an infinitive ; thus va^k-in phāk-nā ka^k , the pigs-by eaten husks .</text><annotationSet ID="26472" luID="28337" luName="verb.n" frameID="1244" frameName="verbal"><layer name="fe"><label ID="11596" name="subclass" start="18" end="27"/><label ID="11596" name="subclass" start="35" end="44"/><label ID="11594" name="data" start="53" end="72"/><label ID="11595" name="data_translation" start="76" end="98"/></layer><layer name="target"><label ID="1" name="Target" start="4" end="7"/></layer></annotationSet></sentence><sentence ID="16644"><text>The Genitive is expressed by putting the stem , without any suffix , or repeated by means of a pronoun , before the governing noun ; thus , nang-mā pā nāi , thy father ’ s sons ; mā sā-kor ā-kūm ī-jā-kā-ma^ , this horse its years how-many ?</text><annotationSet ID="27043" luID="28411" luName="genitive.n" frameID="1266" frameName="case_property"><layer name="target"><label ID="1" name="Target" start="4" end="11"/></layer></annotationSet><annotationSet ID="27044" luID="28302" luName="stem.n" frameID="1231" frameName="morpheme"><layer name="target"><label ID="1" name="Target" start="41" end="44"/></layer></annotationSet><annotationSet ID="27045" luID="28379" luName="noun.n" frameID="1255" frameName="noun"><layer name="fe"><label ID="11661" name="subclass" start="116" end="124"/></layer><layer name="target"><label ID="1" name="Target" start="126" end="129"/></layer></annotationSet><annotationSet ID="27046" luID="28334" luName="pronoun.n" frameID="1243" frameName="pronominal"><layer name="target"><label ID="1" name="Target" start="95" end="101"/></layer></annotationSet></sentence><sentence ID="16645"><text>The suffix tā is sometimes added ; thus , kai-mā pā-tā lō-mūnā sēla^-hēi , my father ’ s hired servants .</text><annotationSet ID="27048" luID="28347" luName="suffix.v" frameID="1246" frameName="affixation"><layer name="fe"><label ID="11612" name="data" start="11" end="12"/></layer><layer name="target"><label ID="1" name="Target" start="4" end="9"/></layer></annotationSet></sentence><sentence ID="16646"><text>The Locative is formed by means of the suffixes ā and in .</text><annotationSet ID="27049" luID="28381" luName="form.v" frameID="1256" frameName="formation"><layer name="fe"><label ID="11662" name="formed_entity" start="0" end="11"/><label ID="11664" name="process" start="23" end="55"/></layer><layer name="target"><label ID="1" name="Target" start="16" end="21"/></layer></annotationSet></sentence><sentence ID="16647"><text>In is also used to denote the agent ( see above ) and the instrument ; thus , rū-in , ( bind ) with ropes .</text></sentence><sentence ID="16648"><text>Other postpositions used to denote the various relations of nouns are .</text><annotationSet ID="27446" luID="28379" luName="noun.n" frameID="1255" frameName="noun"><layer name="target"><label ID="1" name="Target" start="60" end="64"/></layer></annotationSet></sentence><sentence ID="16649"><text>lāi-ā , between ; nai-ā , under ; mā-teng , before ; nēng , in , for ; nēng-ā , in , to , from ; nūng-ā , behind ; pōā , out of ; rōal-in , gathering , with ; rū-ai , from ; sūng-ā , in ; tai-ā , in , etc.</text></sentence><sentence ID="16650"><text>Adjectives .</text><annotationSet ID="27119" luID="28375" luName="adjective.n" frameID="1254" frameName="adjectival"><layer name="target"><label ID="1" name="Target" start="0" end="9"/></layer></annotationSet></sentence><sentence ID="16651"><text>Adjectives usually follow the noun they qualify , and suffixes are then added to them and not to the qualified noun .</text><annotationSet ID="27120" luID="28375" luName="adjective.n" frameID="1254" frameName="adjectival"><layer name="target"><label ID="1" name="Target" start="0" end="9"/></layer></annotationSet><annotationSet ID="27441" luID="28379" luName="noun.n" frameID="1255" frameName="noun"><layer name="fe"><label ID="11661" name="subclass" start="101" end="109"/></layer><layer name="target"><label ID="1" name="Target" start="111" end="114"/></layer></annotationSet><annotationSet ID="27444" luID="28389" luName="suffix.n" frameID="1258" frameName="affix"><layer name="target"><label ID="1" name="Target" start="54" end="61"/></layer></annotationSet><annotationSet ID="27445" luID="28379" luName="noun.n" frameID="1255" frameName="noun"><layer name="target"><label ID="1" name="Target" start="30" end="33"/></layer></annotationSet><annotationSet ID="31224" luID="28436" luName="follow.v" frameID="1271" frameName="frm_sequence"><layer name="fe"><label ID="11730" name="fe_Entity_1" start="0" end="9"/><label ID="11736" name="fe_Frequency" start="11" end="17"/><label ID="11733" name="fe_Order" start="19" end="24"/><label ID="11731" name="fe_Entity_2" start="26" end="33"/></layer><layer name="target"><label ID="1" name="Target" start="19" end="24"/></layer></annotationSet></sentence><sentence ID="16652"><text>Thus , mī ṭhā nēng-ā , man good to .</text></sentence><sentence ID="16653"><text>The suffix of comparison is nēk-in or ning-in .</text><annotationSet ID="27439" luID="28389" luName="suffix.n" frameID="1258" frameName="affix"><layer name="fe"><label ID="11677" name="subclass" start="11" end="23"/><label ID="11678" name="data" start="28" end="44"/></layer><layer name="target"><label ID="1" name="Target" start="4" end="9"/></layer></annotationSet></sentence><sentence ID="16654"><text>Thus , ā far-nū nēk-in ān-sang , his sister than tall ; rēn-kā ning-in pōan ṭhā , all than cloth good .</text></sentence><sentence ID="16655"><text>Numerals .</text><annotationSet ID="27454" luID="28306" luName="numeral.n" frameID="1232" frameName="numeral"><layer name="target"><label ID="1" name="Target" start="0" end="7"/></layer></annotationSet></sentence><sentence ID="16656"><text>The numerals are given in the list of words .</text><annotationSet ID="27455" luID="28306" luName="numeral.n" frameID="1232" frameName="numeral"><layer name="target"><label ID="1" name="Target" start="4" end="11"/></layer></annotationSet></sentence><sentence ID="16657"><text>They follow the noun they qualify .</text><annotationSet ID="27456" luID="28379" luName="noun.n" frameID="1255" frameName="noun"><layer name="target"><label ID="1" name="Target" start="16" end="19"/></layer></annotationSet><annotationSet ID="31225" luID="28436" luName="follow.v" frameID="1271" frameName="frm_sequence"><layer name="fe"><label ID="11730" name="fe_Entity_1" start="0" end="3"/><label ID="11733" name="fe_Order" start="5" end="10"/><label ID="11731" name="fe_Entity_2" start="12" end="19"/></layer><layer name="target"><label ID="1" name="Target" start="5" end="10"/></layer></annotationSet></sentence><sentence ID="16658"><text>Pā in pā-kāt , one , etc., is probably a generic particle .</text><annotationSet ID="27440" luID="28315" luName="particle.n" frameID="1235" frameName="particle"><layer name="fe"><label ID="11541" name="subclass" start="41" end="47"/></layer><layer name="target"><label ID="1" name="Target" start="49" end="56"/></layer></annotationSet></sentence><sentence ID="16659"><text>But I cannot find any rule for its use .</text></sentence><sentence ID="16660"><text>Thus we find mi-rēm pā-kāt and mi khāt-kā , one man , Kā in khāt-kā , etc., is perhaps identical with the kā in words such as jā-kā , whatever ; rēng-kā , all ; tai-kā , short ; lām-kā , much ; ī-kā , any ; āng-kā , like , etc.</text></sentence><sentence ID="16661"><text>Pronouns .</text><annotationSet ID="27436" luID="28334" luName="pronoun.n" frameID="1243" frameName="pronominal"><layer name="target"><label ID="1" name="Target" start="0" end="7"/></layer></annotationSet></sentence><sentence ID="16662"><text>The following are the Personal pronouns , to which the ordinary suffixes may be added : To these forms must be added the pronominal prefixes used before verbs .</text><annotationSet ID="27435" luID="28334" luName="pronoun.n" frameID="1243" frameName="pronominal"><layer name="fe"><label ID="11591" name="sublass" start="22" end="29"/></layer><layer name="target"><label ID="1" name="Target" start="31" end="38"/></layer></annotationSet><annotationSet ID="27437" luID="28389" luName="suffix.n" frameID="1258" frameName="affix"><layer name="fe"><label ID="11677" name="subclass" start="55" end="62"/></layer><layer name="target"><label ID="1" name="Target" start="64" end="71"/></layer></annotationSet><annotationSet ID="27438" luID="28346" luName="prefix.v" frameID="1246" frameName="affixation"><layer name="fe"><label ID="11610" name="position" start="141" end="157"/><label ID="11604" name="anthropomorphic_entity" start="121" end="130"/></layer><layer name="target"><label ID="1" name="Target" start="132" end="139"/></layer></annotationSet><annotationSet ID="27443" luID="28337" luName="verb.n" frameID="1244" frameName="verbal"><layer name="target"><label ID="1" name="Target" start="153" end="157"/></layer></annotationSet></sentence><sentence ID="16663"><text>In the singular they are identical with the short possessive forms , kē , nai , ā .</text></sentence><sentence ID="16664"><text>The plural forms are kāin , nāin , and ān-in or ān , and these may probably also be used as possessive pronouns with nouns and postpositions .</text><annotationSet ID="27432" luID="28323" luName="plural.n" frameID="1239" frameName="number_property"><layer name="fe"><label ID="11553" name="subclass" start="11" end="15"/></layer><layer name="target"><label ID="1" name="Target" start="4" end="9"/></layer></annotationSet><annotationSet ID="27433" luID="28334" luName="pronoun.n" frameID="1243" frameName="pronominal"><layer name="fe"><label ID="11591" name="sublass" start="92" end="101"/></layer><layer name="target"><label ID="1" name="Target" start="103" end="110"/></layer></annotationSet><annotationSet ID="27434" luID="28379" luName="noun.n" frameID="1255" frameName="noun"><layer name="target"><label ID="1" name="Target" start="117" end="121"/></layer></annotationSet></sentence><sentence ID="16665"><text>The following Demonstrative pronouns occur : Hā , this ; hi , this ; mā , that ; sa^ , that ; mā-hi , that , he .</text><annotationSet ID="27431" luID="28334" luName="pronoun.n" frameID="1243" frameName="pronominal"><layer name="fe"><label ID="11589" name="data" start="94" end="98"/><label ID="11590" name="data_translation" start="102" end="105"/><label ID="11591" name="sublass" start="14" end="26"/><label ID="11590" name="data_translation" start="109" end="110"/><label ID="11589" name="data" start="45" end="46"/><label ID="11590" name="data_translation" start="50" end="53"/><label ID="11589" name="data" start="57" end="58"/><label ID="11590" name="data_translation" start="62" end="65"/><label ID="11589" name="data" start="69" end="70"/><label ID="11590" name="data_translation" start="74" end="77"/><label ID="11589" name="data" start="81" end="83"/><label ID="11590" name="data_translation" start="87" end="90"/></layer><layer name="target"><label ID="1" name="Target" start="28" end="35"/></layer></annotationSet></sentence><sentence ID="16666"><text>Relative pronouns .</text><annotationSet ID="27430" luID="28334" luName="pronoun.n" frameID="1243" frameName="pronominal"><layer name="fe"><label ID="11591" name="sublass" start="0" end="7"/></layer><layer name="target"><label ID="1" name="Target" start="9" end="16"/></layer></annotationSet></sentence><sentence ID="16667"><text>Participles and verbal nouns are used in relative clauses ; thus , va^k-in phāk-nā ka^k , pigs-by eaten husks ; mā ha^ng-tik-in , he coming-time-at .</text><annotationSet ID="27428" luID="28379" luName="noun.n" frameID="1255" frameName="noun"><layer name="fe"><label ID="11661" name="subclass" start="0" end="21"/></layer><layer name="target"><label ID="1" name="Target" start="23" end="27"/></layer></annotationSet><annotationSet ID="27429" luID="28320" luName="clause.n" frameID="1238" frameName="clause"><layer name="fe"><label ID="11550" name="subclass" start="41" end="48"/></layer><layer name="target"><label ID="1" name="Target" start="50" end="56"/></layer></annotationSet></sentence><sentence ID="16668"><text>Interrogative pronounṣ Tū-ma^ , who ?</text><annotationSet ID="27427" luID="28334" luName="pronoun.n" frameID="1243" frameName="pronominal"><layer name="fe"><label ID="11591" name="sublass" start="0" end="12"/><label ID="11589" name="data" start="23" end="28"/><label ID="11590" name="data_translation" start="32" end="34"/></layer><layer name="target"><label ID="1" name="Target" start="14" end="21"/></layer></annotationSet></sentence><sentence ID="16669"><text>ī-ma^ , what ?</text></sentence><sentence ID="16670"><text>ī-jā-kā-ma^ , how many ?</text></sentence><sentence ID="16671"><text>i-ding-ma^ , why ?</text></sentence><sentence ID="16672"><text>Thus , tū-nāi-ma^ , whose son ?</text></sentence><sentence ID="16673"><text>mā-hēi ī-ma^ , these what ?</text></sentence><sentence ID="16674"><text>Indefinite pronounṣ Īkā , any ; tū-kha^m , anyone .</text><annotationSet ID="27426" luID="28334" luName="pronoun.n" frameID="1243" frameName="pronominal"><layer name="fe"><label ID="11591" name="sublass" start="0" end="9"/><label ID="11589" name="data" start="20" end="22"/><label ID="11590" name="data_translation" start="26" end="28"/><label ID="11589" name="data" start="32" end="39"/><label ID="11590" name="data_translation" start="43" end="48"/></layer><layer name="target"><label ID="1" name="Target" start="11" end="18"/></layer></annotationSet></sentence><sentence ID="16675"><text>Kha^m in tū-kha^m seems to mean ‘ even ’ ; thus , tik-tik-kha^m , time-time-even , once even .</text></sentence><sentence ID="16676"><text>Verbs .</text><annotationSet ID="27425" luID="28337" luName="verb.n" frameID="1244" frameName="verbal"><layer name="target"><label ID="1" name="Target" start="0" end="4"/></layer></annotationSet></sentence><sentence ID="16677"><text>Verbs may be conjugated in person and number by means of pronominal prefixes .</text><annotationSet ID="27423" luID="28337" luName="verb.n" frameID="1244" frameName="verbal"><layer name="target"><label ID="1" name="Target" start="0" end="4"/></layer></annotationSet><annotationSet ID="27424" luID="28428" luName="conjugated.a" frameID="1268" frameName="conjugation"><layer name="fe"><label ID="11714" name="verb" start="0" end="4"/><label ID="11715" name="grammatical_category" start="27" end="43"/><label ID="11723" name="means" start="48" end="75"/></layer><layer name="target"><label ID="1" name="Target" start="13" end="22"/></layer></annotationSet></sentence><sentence ID="16678"><text>These are as follows .</text></sentence><sentence ID="16679"><text>kē or kai , I ; kāin , we : nā or nai , thou ; nāin , you : ān or ā , he , she , it ; ān or ān-in , they .</text></sentence><sentence ID="16680"><text>The use of these prefixes is very inconsistent , and they are often dropped .</text><annotationSet ID="27422" luID="28391" luName="prefix.n" frameID="1258" frameName="affix"><layer name="target"><label ID="1" name="Target" start="17" end="24"/></layer></annotationSet></sentence><sentence ID="16681"><text>The root alone , without any suffix , is freely used to denote present and past times .</text><annotationSet ID="27420" luID="28301" luName="root.n" frameID="1231" frameName="morpheme"><layer name="target"><label ID="1" name="Target" start="4" end="7"/></layer></annotationSet><annotationSet ID="27421" luID="28389" luName="suffix.n" frameID="1258" frameName="affix"><layer name="target"><label ID="1" name="Target" start="29" end="34"/></layer></annotationSet></sentence><sentence ID="16682"><text>Thus , kai-mā kāl , I go ; ān-mā-ni lung-ṭlāi-tir , they merry-to-make-began ; kai-mā sir , I have walked ; ā-ni ha^l , he is-grazing .</text></sentence><sentence ID="16683"><text>The suffix of Past tenses is tā ; thus , kai-mān kē hem-tā , I struck ; ān pā-in ā-ni mū-tā , his father him saw .</text><annotationSet ID="27418" luID="28389" luName="suffix.n" frameID="1258" frameName="affix"><layer name="fe"><label ID="11677" name="subclass" start="11" end="24"/><label ID="11678" name="data" start="29" end="30"/></layer><layer name="target"><label ID="1" name="Target" start="4" end="9"/></layer></annotationSet><annotationSet ID="27419" luID="28388" luName="tense.n" frameID="1257" frameName="tense_property"><layer name="fe"><label ID="11672" name="subclass" start="14" end="17"/><label ID="11676" name="data_translation" start="94" end="111"/></layer><layer name="target"><label ID="1" name="Target" start="19" end="24"/></layer></annotationSet></sentence><sentence ID="16684"><text>The suffix of the Future is ding ; thus , kai-mā tha^-in kē pā nēng-ā kāl-ding , I arising my father-to go-will .</text><annotationSet ID="27416" luID="28389" luName="suffix.n" frameID="1258" frameName="affix"><layer name="fe"><label ID="11677" name="subclass" start="11" end="23"/><label ID="11678" name="data" start="28" end="31"/></layer><layer name="target"><label ID="1" name="Target" start="4" end="9"/></layer></annotationSet><annotationSet ID="27417" luID="28386" luName="future.n" frameID="1257" frameName="tense_property"><layer name="fe"><label ID="11676" name="data_translation" start="81" end="110"/></layer><layer name="target"><label ID="1" name="Target" start="18" end="23"/></layer></annotationSet></sentence><sentence ID="16685"><text>The suffix of the Imperative is rō or ra^ ; thus , pē-rō , give ; choy-ra^ , bring , draw ; būn-tir-rō , to-wear-cause you .</text><annotationSet ID="27414" luID="28389" luName="suffix.n" frameID="1258" frameName="affix"><layer name="fe"><label ID="11677" name="subclass" start="11" end="27"/><label ID="11678" name="data" start="32" end="40"/></layer><layer name="target"><label ID="1" name="Target" start="4" end="9"/></layer></annotationSet><annotationSet ID="27415" luID="28407" luName="imperative.n" frameID="1265" frameName="mood_property"><layer name="target"><label ID="1" name="Target" start="18" end="27"/></layer></annotationSet></sentence><sentence ID="16686"><text>A first person plural is formed by means of the suffix rang , probably a suffix of the future .</text><annotationSet ID="27042" luID="28381" luName="form.v" frameID="1256" frameName="formation"><layer name="fe"><label ID="11662" name="formed_entity" start="0" end="20"/><label ID="11664" name="process" start="35" end="58"/><label ID="11664" name="process" start="32" end="34"/></layer><layer name="target"><label ID="1" name="Target" start="25" end="30"/></layer></annotationSet><annotationSet ID="27413" luID="28389" luName="suffix.n" frameID="1258" frameName="affix"><layer name="fe"><label ID="11677" name="subclass" start="80" end="92"/></layer><layer name="target"><label ID="1" name="Target" start="73" end="78"/></layer></annotationSet></sentence><sentence ID="16687"><text>Thus , kai-mā-ni phāk-in lung-ṭlāi-rang , us eating merry-make-let .</text></sentence><sentence ID="16688"><text>See also Infinitive , below .</text></sentence><sentence ID="16689"><text>The simplest form of the Infinitive or Verbal Noun seems to be the root alone .</text><annotationSet ID="27040" luID="28379" luName="noun.n" frameID="1255" frameName="noun"><layer name="fe"><label ID="11661" name="subclass" start="25" end="44"/></layer><layer name="target"><label ID="1" name="Target" start="46" end="49"/></layer></annotationSet><annotationSet ID="27041" luID="28301" luName="root.n" frameID="1231" frameName="morpheme"><layer name="target"><label ID="1" name="Target" start="67" end="70"/></layer></annotationSet></sentence><sentence ID="16690"><text>A common suffix is nā ; thus , kāl-nā , to go ; phāk-nā , to eat , food .</text><annotationSet ID="27039" luID="28389" luName="suffix.n" frameID="1258" frameName="affix"><layer name="fe"><label ID="11678" name="data" start="19" end="20"/><label ID="11678" name="data" start="31" end="36"/><label ID="11725" name="fe_Data_Translation" start="40" end="44"/><label ID="11678" name="data" start="48" end="54"/><label ID="11725" name="fe_Data_Translation" start="58" end="70"/></layer><layer name="target"><label ID="1" name="Target" start="9" end="14"/></layer></annotationSet></sentence><sentence ID="16691"><text>It will be observed that this form is constantly given in the list of words to translate the verbal roots .</text><annotationSet ID="27038" luID="28301" luName="root.n" frameID="1231" frameName="morpheme"><layer name="fe"><label ID="11523" name="subclass" start="93" end="98"/></layer><layer name="target"><label ID="1" name="Target" start="100" end="104"/></layer></annotationSet></sentence><sentence ID="16692"><text>Thus , hong-nā , come ; ngir-nā , stand , etc.</text></sentence><sentence ID="16693"><text>Infinitives of purpose are formed with the suffixes ding and rang ; thus , hal-nā-ding-in , grazing-for ; phūng-kha^f-ding ning-tā , belly-fill-for </text><annotationSet ID="27036" luID="28381" luName="form.v" frameID="1256" frameName="formation"><layer name="fe"><label ID="11662" name="formed_entity" start="0" end="21"/><label ID="11664" name="process" start="34" end="64"/></layer><layer name="target"><label ID="1" name="Target" start="27" end="32"/></layer></annotationSet><annotationSet ID="27037" luID="28389" luName="suffix.n" frameID="1258" frameName="affix"><layer name="fe"><label ID="11678" name="data" start="52" end="55"/><label ID="11678" name="data" start="61" end="64"/><label ID="11678" name="data" start="75" end="88"/><label ID="11725" name="fe_Data_Translation" start="92" end="102"/><label ID="11678" name="data" start="106" end="129"/><label ID="11725" name="fe_Data_Translation" start="133" end="146"/></layer><layer name="target"><label ID="1" name="Target" start="43" end="50"/></layer></annotationSet></sentence><sentence ID="16694"><text>wished ; kai-mā ṭēn-hēi rōal-in lung-ṭlāi-rang , my friends with feasting-for .</text></sentence><sentence ID="16695"><text>Compare also ā-ni-ding-in , his-sake-for .</text></sentence><sentence ID="16696"><text>Participles .</text></sentence><sentence ID="16697"><text>The root alone may be considered as a Relative participle in mā ha^ng-tik-in , he coming-time-at .</text></sentence><sentence ID="16698"><text>The same meaning has the verbal noun ending in nā ; thus , va^k-in phāk-nā ka^k , pigs-by eaten husks ; mā ja^l-ā a^m-nā mi , that country-in residing man .</text><annotationSet ID="27035" luID="28379" luName="noun.n" frameID="1255" frameName="noun"><layer name="fe"><label ID="11661" name="subclass" start="25" end="30"/></layer><layer name="target"><label ID="1" name="Target" start="32" end="35"/></layer></annotationSet></sentence><sentence ID="16699"><text>The suffix i-lā is used to form a Conjunctive participle ; thus , bāk-ilā pē-rō , dividing give .</text><annotationSet ID="27033" luID="28347" luName="suffix.v" frameID="1246" frameName="affixation"><layer name="fe"><label ID="11604" name="anthropomorphic_entity" start="11" end="14"/><label ID="11608" name="purpose" start="27" end="55"/><label ID="11612" name="data" start="66" end="78"/><label ID="11617" name="data_translation" start="82" end="94"/></layer><layer name="target"><label ID="1" name="Target" start="4" end="9"/></layer></annotationSet><annotationSet ID="31080" luID="28381" luName="form.v" frameID="1256" frameName="formation"><layer name="fe"><label ID="11664" name="process" start="0" end="14"/><label ID="11662" name="formed_entity" start="34" end="55"/></layer><layer name="target"><label ID="1" name="Target" start="27" end="30"/></layer></annotationSet></sentence><sentence ID="16700"><text>The locative suffixes ā and in form Conjunctive and Adverbial participles .</text><annotationSet ID="27032" luID="28389" luName="suffix.n" frameID="1258" frameName="affix"><layer name="fe"><label ID="11677" name="subclass" start="4" end="11"/><label ID="11678" name="data" start="22" end="22"/></layer><layer name="target"><label ID="1" name="Target" start="13" end="20"/></layer></annotationSet><annotationSet ID="31081" luID="28381" luName="form.v" frameID="1256" frameName="formation"><layer name="fe"><label ID="11664" name="process" start="0" end="29"/><label ID="11662" name="formed_entity" start="36" end="72"/></layer><layer name="target"><label ID="1" name="Target" start="31" end="34"/></layer></annotationSet></sentence><sentence ID="16701"><text>Thus , in-ā nēngā a^m-ā hai-tā , house near being he heard ; kai-mā tha^-in kāl-ding , I arising go-will ; phāk-in lung-ṭlāi-rang , eating let-us-rejoice .</text></sentence><sentence ID="16702"><text>The second specimen uses ē instead of in ; thus , sōal-ē , being tired .</text></sentence><sentence ID="16703"><text>There is no Passive voice .</text><annotationSet ID="27031" luID="28292" luName="voice.n" frameID="1227" frameName="voice_property"><layer name="fe"><label ID="11507" name="subclass" start="12" end="18"/></layer><layer name="target"><label ID="1" name="Target" start="20" end="24"/></layer></annotationSet></sentence><sentence ID="16704"><text>The suffix in after the subject of a transitive verb denotes the active .</text><annotationSet ID="27029" luID="28337" luName="verb.n" frameID="1244" frameName="verbal"><layer name="fe"><label ID="11596" name="subclass" start="37" end="46"/></layer><layer name="target"><label ID="1" name="Target" start="48" end="51"/></layer></annotationSet><annotationSet ID="27030" luID="28293" luName="active.n" frameID="1227" frameName="voice_property"><layer name="target"><label ID="1" name="Target" start="65" end="70"/></layer></annotationSet><annotationSet ID="27034" luID="28347" luName="suffix.v" frameID="1246" frameName="affixation"><layer name="fe"><label ID="11610" name="position" start="14" end="51"/></layer><layer name="target"><label ID="1" name="Target" start="4" end="9"/></layer></annotationSet></sentence><sentence ID="16705"><text>But its use is somewhat inconsistent , and its absence does not , therefore , always show that the verb is in the passive voice .</text><annotationSet ID="27027" luID="28337" luName="verb.n" frameID="1244" frameName="verbal"><layer name="fe"><label ID="11596" name="subclass" start="107" end="126"/></layer><layer name="target"><label ID="1" name="Target" start="99" end="102"/></layer></annotationSet><annotationSet ID="27448" luID="28292" luName="voice.n" frameID="1227" frameName="voice_property"><layer name="fe"><label ID="11507" name="subclass" start="114" end="120"/></layer><layer name="target"><label ID="1" name="Target" start="122" end="126"/></layer></annotationSet></sentence><sentence ID="16706"><text>The context must be consulted .</text></sentence><sentence ID="16707"><text>Thus , nāng-mā nāi-bung hi bai-tā nūng-ā mū-tā , thy brother this lost-was afterwards found-was .</text></sentence><sentence ID="16708"><text>Compound verbs .</text><annotationSet ID="27016" luID="28337" luName="verb.n" frameID="1244" frameName="verbal"><layer name="fe"><label ID="11596" name="subclass" start="0" end="7"/></layer><layer name="target"><label ID="1" name="Target" start="9" end="13"/></layer></annotationSet></sentence><sentence ID="16709"><text>No prefixes occur in the specimens .</text><annotationSet ID="27449" luID="28391" luName="prefix.n" frameID="1258" frameName="affix"><layer name="target"><label ID="1" name="Target" start="3" end="10"/></layer></annotationSet></sentence><sentence ID="16710"><text>Causatives are formed by means of the verb tir ; thus , kāl-tir , to cause to go , to send .</text><annotationSet ID="27018" luID="28381" luName="form.v" frameID="1256" frameName="formation"><layer name="fe"><label ID="11662" name="formed_entity" start="0" end="9"/><label ID="11664" name="process" start="25" end="41"/><label ID="11664" name="process" start="43" end="45"/><label ID="11670" name="data_translation" start="56" end="62"/><label ID="11670" name="data_translation" start="66" end="79"/><label ID="11670" name="data_translation" start="83" end="89"/><label ID="11664" name="process" start="22" end="24"/><label ID="11664" name="process" start="42" end="42"/></layer><layer name="target"><label ID="1" name="Target" start="15" end="20"/></layer></annotationSet></sentence><sentence ID="16711"><text>Desideratives are formed by adding na^m , to wish ; thus , kāl-na^m-māk , to-go-wished-not .</text><annotationSet ID="27019" luID="28381" luName="form.v" frameID="1256" frameName="formation"><layer name="fe"><label ID="11662" name="formed_entity" start="0" end="12"/><label ID="11664" name="process" start="28" end="38"/><label ID="11669" name="data" start="59" end="70"/><label ID="11670" name="data_translation" start="74" end="89"/><label ID="11670" name="data_translation" start="42" end="48"/></layer><layer name="target"><label ID="1" name="Target" start="18" end="23"/></layer></annotationSet></sentence><sentence ID="16712"><text>Thēi means ‘ to be able ’ ‘ to be allowed ’ .</text></sentence><sentence ID="16713"><text>Thus , kai om-thēi , I may be .</text></sentence><sentence ID="16714"><text>Other words used as the last part of compound verbs are .</text><annotationSet ID="27020" luID="28337" luName="verb.n" frameID="1244" frameName="verbal"><layer name="fe"><label ID="11596" name="subclass" start="37" end="44"/></layer><layer name="target"><label ID="1" name="Target" start="46" end="50"/></layer></annotationSet></sentence><sentence ID="16715"><text>ēm-ēm , exceedingly ; jā , completely ; khir , back , again ; khul-khul , to be about , etc.</text></sentence><sentence ID="16716"><text>The Negative particle is māk ; thus , kāl-na^m-māk , to-go-wished-not .</text><annotationSet ID="27021" luID="28363" luName="negative.n" frameID="1250" frameName="polarity_property"><layer name="fe"><label ID="11635" name="subclass" start="13" end="20"/></layer><layer name="target"><label ID="1" name="Target" start="4" end="11"/></layer></annotationSet><annotationSet ID="27026" luID="28315" luName="particle.n" frameID="1235" frameName="particle"><layer name="fe"><label ID="11541" name="subclass" start="4" end="11"/><label ID="11542" name="data" start="25" end="27"/><label ID="11542" name="data" start="38" end="49"/><label ID="11543" name="data_translation" start="53" end="68"/></layer><layer name="target"><label ID="1" name="Target" start="13" end="20"/></layer></annotationSet></sentence><sentence ID="16717"><text>Another negative , na , occurs twice after pē , to give ; thus , pē-na , gave not .</text><annotationSet ID="27022" luID="28363" luName="negative.n" frameID="1250" frameName="polarity_property"><layer name="target"><label ID="1" name="Target" start="8" end="15"/></layer></annotationSet></sentence><sentence ID="16718"><text>A third negative , lai , occurs in ā-ṭhā-lai , good-not , bad ; ai-lai , obey-not ; ai-lai-ā , disobeying , against .</text><annotationSet ID="27023" luID="28363" luName="negative.n" frameID="1250" frameName="polarity_property"><layer name="fe"><label ID="11635" name="subclass" start="2" end="6"/></layer><layer name="target"><label ID="1" name="Target" start="8" end="15"/></layer></annotationSet></sentence><sentence ID="16719"><text>The Interrogative particle is ma^ or mō ; thus , tū-nēng-ā ma^ , whom from ?</text><annotationSet ID="27025" luID="28315" luName="particle.n" frameID="1235" frameName="particle"><layer name="fe"><label ID="11541" name="subclass" start="4" end="16"/><label ID="11542" name="data" start="30" end="38"/></layer><layer name="target"><label ID="1" name="Target" start="18" end="25"/></layer></annotationSet></sentence><sentence ID="16720"><text>ī-hang-mo , why ?</text></sentence><sentence ID="16721"><text>because , etc.</text></sentence><sentence ID="16722"><text>See also Interrogative pronouns , above .</text><annotationSet ID="27024" luID="28334" luName="pronoun.n" frameID="1243" frameName="pronominal"><layer name="fe"><label ID="11591" name="sublass" start="9" end="21"/></layer><layer name="target"><label ID="1" name="Target" start="23" end="30"/></layer></annotationSet></sentence></fullTextAnnotation>
