<?xml version="1.0" encoding="UTF-8" standalone="yes"?>
<?xml-stylesheet type="text/xsl" href="fullText.xsl"?>
<fullTextAnnotation xmlns="http://framenet.icsi.berkeley.edu" xmlns:xsi="http://www.w3.org/2001/XMLSchema-instance" xsi:schemaLocation="../schema/fullText.xsd">
    <header>
        <corpus description="LSI" name="LSI" ID="1">
            <document description="lsi_vol3_p1_tibeto-burman_murmi" name="lsi_vol3_p1_tibeto-burman_murmi" ID="30"/>
        </corpus>
    </header>
<sentence ID="14772"><text>MURMI .</text></sentence><sentence ID="14773"><text>The Murmis claim to be among the earliest settlers of Nepal .</text></sentence><sentence ID="14774"><text>According to Sir Herbert Risley , ‘ their physical characteristics , and the fact that their exogamous divisions ( thars ) bear Tibetan names , seem to lend support to the opinion that they are descended from a Tibetan stock , modified more or less by intermixture with Nepalese races ’ .</text></sentence><sentence ID="14775"><text>The Murmis are also known under other names , such as Tāmāng Bhōṭiā , Ishāng , and Sain .</text></sentence><sentence ID="14776"><text>The home of the Murmi tribe is the valley of Nepal and its whole vicinity .</text></sentence><sentence ID="14777"><text>They are further found in considerable numbers in Darjeeling and Sikkim .</text></sentence><sentence ID="14778"><text>Number of speakers .</text></sentence><sentence ID="14779"><text>We have no information about the number of speakers in Nepal .</text></sentence><sentence ID="14780"><text>Their number in Darjeeling and Sikkim was estimated for the purposes of this Survey as follows .</text></sentence><sentence ID="14781"><text>At the last Census of 1901 , Murmi was returned from the following districts : The Census figures show that the local estimates from Sikkim are considerably above the mark .</text></sentence><sentence ID="14782"><text>AUTHORITIES Campbell , A ., Notes on the Limboos and other Hill Tribes hitherto undescribed .</text></sentence><sentence ID="14783"><text>Journal of the Asiatic Society of Bengal , Vol .</text></sentence><sentence ID="14784"><text>ix , Part i , 1840 , pp .</text></sentence><sentence ID="14785"><text>595 and ff.</text></sentence><sentence ID="14786"><text>Contains a Moormi vocabulary .</text></sentence><sentence ID="14787"><text>Hodgson , B .H ., On the Aborigines of the Sub-Himalayas .</text></sentence><sentence ID="14788"><text>Journal of the Asiatic Society of Bengal , Vol .</text></sentence><sentence ID="14789"><text>xvi , Part ii , 1847 , pp .</text></sentence><sentence ID="14790"><text>1235 and ff.</text></sentence><sentence ID="14791"><text>Reprinted in Selections from the Records of the Government of Bengal , No .</text></sentence><sentence ID="14792"><text>xxvii , Calcutta , 1857 , pp .</text></sentence><sentence ID="14793"><text>126 and ff., and , under the title On the Aborigines of the Himalaya , in Hodgson ’ s Essays on the Languages , Literature , and Religion of Nepăl and Tibet .</text></sentence><sentence ID="14794"><text>London , 1874 .</text></sentence><sentence ID="14795"><text>Part ii , pp .</text></sentence><sentence ID="14796"><text>29 and ff.</text></sentence><sentence ID="14797"><text>Contains Murmi vocabularies .</text></sentence><sentence ID="14798"><text>Beames , J ., Outlines of Indian Philology , with a Map shewing the Distribution of Indian Languages .</text></sentence><sentence ID="14799"><text>Calcutta , 1867 .</text></sentence><sentence ID="14800"><text>Appendix A contains numerals in Murmi .</text></sentence><sentence ID="14801"><text>Hunter , W.W., A Comparative Dictionary of the Languages of India and High Asia .</text></sentence><sentence ID="14802"><text>London , 1868 .</text></sentence><sentence ID="14803"><text>Dalton , Edward Tuite , Descriptive Ethnology of Bengal .</text></sentence><sentence ID="14804"><text>Calcutta , 1872 .</text></sentence><sentence ID="14805"><text>Contains a Murmi vocabulary after Campbell and Hodgson .</text></sentence><sentence ID="14806"><text>Specimens of Murmi have been forwarded from Nepal and Darjeeling .</text></sentence><sentence ID="14807"><text>A version of the Parable of the Prodigal Son and a list of Standard Words and Phrases from Nepal and a popular tale from Darjeeling will be reproduced below .</text></sentence><sentence ID="14808"><text>The materials forwarded for the purposes of this Survey are the only basis of the remarks on Murmi grammar which follow .</text></sentence><sentence ID="14809"><text>Murmi is very closely related to Gurung .</text></sentence><sentence ID="14810"><text>Like that latter form of speech it is more intimately connected with Tibetan than are most other Himalayan dialects .</text></sentence><sentence ID="14811"><text>Pronunciation .</text></sentence><sentence ID="14812"><text>The phonetical system is mainly the same as in Gurung .</text></sentence><sentence ID="14813"><text>Forms such as kwān , Tibetan gon , cloth ; chā , Tibetan za , eat ; pli and bli , Tibetan bzhi , four ; pre and bre , Tibetan brgyad , eight , and so forth , in which hard and soft consonants interchange , seem to show that the soft consonants of Tibetan have developed into soft aspirates , and further into hard sounds .</text><annotationSet ID="25245" luID="28398" luName="consonant.n" frameID="1263" frameName="segment"><layer name="fe"><label ID="11695" name="subclass" start="167" end="170"/><label ID="11695" name="subclass" start="176" end="179"/><label ID="11698" name="language_variety" start="247" end="253"/></layer><layer name="target"><label ID="1" name="Target" start="181" end="190"/></layer></annotationSet></sentence><sentence ID="14814"><text>The final consonants of classical Tibetan have been retained to a greater extent than is the case in Gurung .</text><annotationSet ID="25246" luID="28398" luName="consonant.n" frameID="1263" frameName="segment"><layer name="fe"><label ID="11695" name="subclass" start="4" end="8"/><label ID="11698" name="language_variety" start="34" end="40"/><label ID="11698" name="language_variety" start="101" end="106"/><label ID="11696" name="position" start="0" end="2"/></layer><layer name="target"><label ID="1" name="Target" start="10" end="19"/></layer></annotationSet></sentence><sentence ID="14815"><text>Thus , rop , Tibetan rgyab , beat ; sat , Tibetan gsod , kill ; thung , Tibetan thung , drink ; kwān , Tibetan gon , cloth .</text></sentence><sentence ID="14816"><text>There is , however , the same tendency to drop such sounds as is observed in Gurung .</text></sentence><sentence ID="14817"><text>Compare thā-ring , Tibetan thag-ring , far ; rho , Tibetan grogs , friend ; so , Tibetan gson , alive ; the , Tibetan thos , hear ; mui , Tibetan dngul , mul , silver .</text></sentence><sentence ID="14818"><text>There are several compound consonants such as kl , gl , pl , bl , ml , kr , gr , pr , br , mr , ky , gy , jy , and so forth .</text><annotationSet ID="26449" luID="28282" luName="consonant.n" frameID="1225" frameName="form_unit"><layer name="fe"><label ID="11496" name="data" start="86" end="87"/><label ID="11496" name="data" start="91" end="92"/><label ID="11494" name="subclass" start="18" end="25"/><label ID="11496" name="data" start="96" end="97"/><label ID="11496" name="data" start="46" end="47"/><label ID="11496" name="data" start="101" end="102"/><label ID="11496" name="data" start="51" end="52"/><label ID="11496" name="data" start="106" end="107"/><label ID="11496" name="data" start="56" end="57"/><label ID="11496" name="data" start="61" end="62"/><label ID="11496" name="data" start="66" end="67"/><label ID="11496" name="data" start="71" end="72"/><label ID="11496" name="data" start="76" end="77"/><label ID="11496" name="data" start="81" end="82"/></layer><layer name="target"><label ID="1" name="Target" start="27" end="36"/></layer></annotationSet></sentence><sentence ID="14819"><text>Thus , the klā-ā-ri , that place in ; glā-gi-ri-n , place-one-in , with ; pli and bli , four ; mrāng , see ; kyang-no , all , and so forth .</text></sentence><sentence ID="14820"><text>Many old compounds have , however , been simplified .</text></sentence><sentence ID="14821"><text>G has been dropped in compounds such as gr , gs , and rgy ; thus , rho , classical Tibetan grogs , friend ; so , classical gson , alive ; sat , classical gsod , kill ; rop , classical rgyab , beat ; pre , classical brgyad , eight .</text></sentence><sentence ID="14822"><text>Initial r and s have been dropped in forms such as tā , classical rta , horse ; uhā , classical rna , nose ; kra , classical skra , hair ; pin , classical sbyin , give .</text></sentence><sentence ID="14823"><text>Note also le , classical lche , tongue ; lā , classical lha , god , lā-ni , classical zla , moon , and so forth .</text></sentence><sentence ID="14824"><text>Mr apparently corresponds to classical mth in mrāng , Tibetan mthong-ba , see ; mrin , Tibetan mthon-po , full .</text></sentence><sentence ID="14825"><text>Compare Burmese mrang , to see ; mrüng , to be full .</text></sentence><sentence ID="14826"><text>There is apparently also a certain connexion between dhim , tim , and Tibetan khyim , a house .</text></sentence><sentence ID="14827"><text>We have no information about tones or accentuation .</text><annotationSet ID="26450" luID="28317" luName="tone.n" frameID="1236" frameName="tone_property"><layer name="fe"><label ID="11546" name="data" start="8" end="21"/></layer><layer name="target"><label ID="1" name="Target" start="29" end="33"/></layer></annotationSet></sentence><sentence ID="14828"><text>Article .</text></sentence><sentence ID="14829"><text>There are no articles , but the numeral ki , gi , one , is often used as a kind of indefinite article ; thus , ā-bā-ki , a father ; jhyā-bā ki mhi , a good man ; ki jhyā-bā mi-lā , of a good man .</text><annotationSet ID="26451" luID="28340" luName="article.n" frameID="1245" frameName="article"><layer name="target"><label ID="1" name="Target" start="13" end="20"/></layer></annotationSet><annotationSet ID="26452" luID="28340" luName="article.n" frameID="1245" frameName="article"><layer name="fe"><label ID="11600" name="subclass" start="83" end="92"/></layer><layer name="target"><label ID="1" name="Target" start="94" end="100"/></layer></annotationSet><annotationSet ID="26453" luID="28306" luName="numeral.n" frameID="1232" frameName="numeral"><layer name="fe"><label ID="11529" name="data" start="40" end="41"/><label ID="11529" name="data" start="45" end="46"/><label ID="11527" name="data_translation" start="50" end="52"/></layer><layer name="target"><label ID="1" name="Target" start="32" end="38"/></layer></annotationSet></sentence><sentence ID="14830"><text>It will be seen that ki sometimes precedes and sometimes follows the qualified noun .</text><annotationSet ID="26454" luID="28379" luName="noun.n" frameID="1255" frameName="noun"><layer name="target"><label ID="1" name="Target" start="79" end="82"/></layer></annotationSet></sentence><sentence ID="14831"><text>Nouns .</text><annotationSet ID="26455" luID="28379" luName="noun.n" frameID="1255" frameName="noun"><layer name="target"><label ID="1" name="Target" start="0" end="4"/></layer></annotationSet></sentence><sentence ID="14832"><text>The prefix ā is common in words denoting relationship ; thus , ā-bā , father ; ā-mā , mother ; ā-lā , younger brother ; ā-ngā , younger sister ; ā-gu , uncle .</text><annotationSet ID="26456" luID="28391" luName="prefix.n" frameID="1258" frameName="affix"><layer name="fe"><label ID="11678" name="data" start="11" end="11"/></layer><layer name="target"><label ID="1" name="Target" start="4" end="9"/></layer></annotationSet></sentence><sentence ID="14833"><text>Gender .</text><annotationSet ID="28730" luID="28364" luName="gender.n " frameID="1251" frameName="gender_property"><layer name="target"><label ID="1" name="Target" start="1" end="5"/></layer></annotationSet></sentence><sentence ID="14834"><text>The natural gender can be distinguished by using different words or by adding words such as hvā-bā , male ; me and māmā , female ; thus , mhi , man ; mring-kolā , woman : jhā , son ; jha-me , daughter : tā , horse ; tā-māmā , mare .</text><annotationSet ID="26457" luID="28364" luName="gender.n " frameID="1251" frameName="gender_property"><layer name="fe"><label ID="11637" name="subclass" start="4" end="10"/></layer><layer name="target"><label ID="1" name="Target" start="12" end="17"/></layer></annotationSet></sentence><sentence ID="14835"><text>tāngi hvā-bā , male deer ; tāngi māmā , female deer .</text></sentence><sentence ID="14836"><text>Numbers .</text></sentence><sentence ID="14837"><text>The number is not indicated if it appears from the context .</text></sentence><sentence ID="14838"><text>If it is necessary to distinguish the plural , words such as kāde , kāte , or gāde , many ; dugu ( Tibetan dgu ) , many , are added .</text><annotationSet ID="26458" luID="28323" luName="plural.n" frameID="1239" frameName="number_property"><layer name="fe"><label ID="11554" name="data" start="61" end="64"/><label ID="11554" name="data" start="68" end="71"/><label ID="11554" name="data" start="78" end="81"/><label ID="11555" name="data_translation" start="85" end="88"/><label ID="11554" name="data" start="92" end="95"/><label ID="11556" name="language_variety" start="99" end="105"/><label ID="11554" name="data" start="107" end="109"/><label ID="11555" name="data_translation" start="115" end="118"/></layer><layer name="target"><label ID="1" name="Target" start="38" end="43"/></layer></annotationSet></sentence><sentence ID="14839"><text>Thus , ā-bā kāde , fathers ; chākara dugu , servants .</text></sentence><sentence ID="14840"><text>Case .</text></sentence><sentence ID="14841"><text>The subject of intransitive verbs and the object are not distinguished by adding any suffix .</text><annotationSet ID="26460" luID="28337" luName="verb.n" frameID="1244" frameName="verbal"><layer name="fe"><label ID="11596" name="subclass" start="15" end="26"/></layer><layer name="target"><label ID="1" name="Target" start="28" end="32"/></layer></annotationSet><annotationSet ID="26461" luID="28389" luName="suffix.n" frameID="1258" frameName="affix"><layer name="target"><label ID="1" name="Target" start="85" end="90"/></layer></annotationSet></sentence><sentence ID="14842"><text>The subject of transitive verbs is usually put in the case of the agent , which is formed by adding se ; thus , chāng-bā-se pān-ji , the younger-by said , the younger said .</text><annotationSet ID="26462" luID="28337" luName="verb.n" frameID="1244" frameName="verbal"><layer name="fe"><label ID="11596" name="subclass" start="15" end="24"/></layer><layer name="target"><label ID="1" name="Target" start="26" end="30"/></layer></annotationSet><annotationSet ID="26463" luID="28381" luName="form.v" frameID="1256" frameName="formation"><layer name="fe"><label ID="11671" name="condition" start="47" end="70"/><label ID="11664" name="process" start="90" end="98"/><label ID="11669" name="data" start="100" end="101"/><label ID="11662" name="formed_entity" start="4" end="30"/></layer><layer name="target"><label ID="1" name="Target" start="83" end="88"/></layer></annotationSet></sentence><sentence ID="14843"><text>Instead of se we sometimes find chhe ; thus , āp-chhe , by the father .</text></sentence><sentence ID="14844"><text>In phāyen-ji , from hunger , hungering , ji appears to have been used instead .</text></sentence><sentence ID="14845"><text>Compare Gurung .</text></sentence><sentence ID="14846"><text>The same suffix is also used to denote the instrument .</text><annotationSet ID="26560" luID="28389" luName="suffix.n" frameID="1258" frameName="affix"><layer name="target"><label ID="1" name="Target" start="9" end="14"/></layer></annotationSet><annotationSet ID="34614" luID="28448" luName="use.v" frameID="1274" frameName="frm_using"><layer name="fe"><label ID="11745" name="fe_Entity" start="0" end="14"/><label ID="11747" name="fe_Purpose" start="29" end="52"/></layer><layer name="target"><label ID="1" name="Target" start="24" end="27"/></layer></annotationSet></sentence><sentence ID="14847"><text>Thus , chho-se , with ropes .</text></sentence><sentence ID="14848"><text>The form </text></sentence><sentence ID="14849"><text>nyāī , by me , seems to show that the suffix of this case is originally s , which has become i after a preceding vowel .</text><annotationSet ID="28731" luID="28389" luName="suffix.n" frameID="1258" frameName="affix"><layer name="fe"><label ID="11678" name="data" start="72" end="72"/><label ID="11678" name="data" start="93" end="93"/></layer><layer name="target"><label ID="1" name="Target" start="38" end="43"/></layer></annotationSet></sentence><sentence ID="14850"><text>The suffix of the dative is dā or tā ; thus , ā-bā ki-dā , to a father ; chākara-tā , to a servant .</text><annotationSet ID="26562" luID="28389" luName="suffix.n" frameID="1258" frameName="affix"><layer name="fe"><label ID="11678" name="data" start="28" end="29"/><label ID="11678" name="data" start="34" end="35"/></layer><layer name="target"><label ID="1" name="Target" start="4" end="9"/></layer></annotationSet><annotationSet ID="28732" luID="28410" luName="dative.n" frameID="1266" frameName="case_property"><layer name="target"><label ID="1" name="Target" start="18" end="23"/></layer></annotationSet></sentence><sentence ID="14851"><text>This form is sometimes also used as an accusative ; thus , the-lā jha-tā rop-chi , his son-to struck , I have beaten his son .</text><annotationSet ID="34615" luID="28448" luName="use.v" frameID="1274" frameName="frm_using"><layer name="fe"><label ID="11745" name="fe_Entity" start="0" end="8"/><label ID="11746" name="fe_Role" start="33" end="48"/></layer><layer name="target"><label ID="1" name="Target" start="28" end="31"/></layer></annotationSet></sentence><sentence ID="14852"><text>The suffix of the genitive is lā ; compare Gurung .</text><annotationSet ID="26563" luID="28411" luName="genitive.n" frameID="1266" frameName="case_property"><layer name="target"><label ID="1" name="Target" start="18" end="25"/></layer></annotationSet><annotationSet ID="26564" luID="28389" luName="suffix.n" frameID="1258" frameName="affix"><layer name="fe"><label ID="11678" name="data" start="30" end="31"/><label ID="11679" name="language_variety" start="43" end="48"/></layer><layer name="target"><label ID="1" name="Target" start="4" end="9"/></layer></annotationSet></sentence><sentence ID="14853"><text>Thus , ansa-bhāg-lā , of the share .</text></sentence><sentence ID="14854"><text>A locative and terminative is formed by adding ri as in Gurung ; thus , yāmbunāg-ri , in a city ; dim-ri , in the house ; khāre-ri , upon the neck .</text><annotationSet ID="26565" luID="28381" luName="form.v" frameID="1256" frameName="formation"><layer name="fe"><label ID="11662" name="formed_entity" start="2" end="9"/><label ID="11662" name="formed_entity" start="15" end="25"/><label ID="11664" name="process" start="37" end="45"/><label ID="11669" name="data" start="47" end="48"/><label ID="11668" name="reference_language" start="56" end="61"/></layer><layer name="target"><label ID="1" name="Target" start="30" end="35"/></layer></annotationSet><annotationSet ID="26566" luID="28413" luName="locative.n" frameID="1266" frameName="case_property"><layer name="target"><label ID="1" name="Target" start="2" end="9"/></layer></annotationSet><annotationSet ID="26567" luID="28416" luName="terminative.n" frameID="1266" frameName="case_property"><layer name="target"><label ID="1" name="Target" start="15" end="25"/></layer></annotationSet></sentence><sentence ID="14855"><text>Other relations are indicated by adding postpositions .</text><annotationSet ID="34616" luID="28443" luName="indicate.v" frameID="1272" frameName="Sign"><layer name="fe"><label ID="11741" name="fe_Indicated" start="0" end="14"/><label ID="11740" name="fe_Indicator" start="30" end="52"/></layer><layer name="target"><label ID="1" name="Target" start="20" end="28"/></layer></annotationSet><annotationSet ID="34616" luID="28443" luName="indicate.v" frameID="1272" frameName="frm_sign"><layer name="fe"><label ID="11741" name="fe_Indicated" start="0" end="14"/><label ID="11740" name="fe_Indicator" start="30" end="52"/></layer><layer name="target"><label ID="1" name="Target" start="20" end="28"/></layer></annotationSet></sentence><sentence ID="14856"><text>Such are āng-ri , into ; chhyām and den-chhyām , with , together with ; den , de~ , with ; dhiri , under ; kyām , kyāmse , from ; lāgi , for ; mā , in , among ; thāri , upon , against ; yenchhe and yenji , from , and so forth .</text></sentence><sentence ID="14857"><text>Some postpositions are added to the genitive ; thus , li-chhā and li-sang , behind ; ngā-chhā , behind ; nindi-ri , for the sake of .</text><annotationSet ID="26568" luID="28411" luName="genitive.n" frameID="1266" frameName="case_property"><layer name="target"><label ID="1" name="Target" start="36" end="43"/></layer></annotationSet></sentence><sentence ID="14858"><text>A suffix b or p of uncertain meaning occurs in several words such as cheta-p ta-si-jin-ji , having come to senses ; chhuṭya-p la-si , division making ; lhābā-b tā-ji , engaged ; mānasi-b tā-si , it became proper ; pheriā-b ā-si , coming outside ; uḍa-b lā-si , squandered .</text><annotationSet ID="26569" luID="28389" luName="suffix.n" frameID="1258" frameName="affix"><layer name="fe"><label ID="11678" name="data" start="9" end="9"/><label ID="11678" name="data" start="14" end="14"/></layer><layer name="target"><label ID="1" name="Target" start="2" end="7"/></layer></annotationSet></sentence><sentence ID="14859"><text>Adjectives .</text><annotationSet ID="28733" luID="28375" luName="adjective.n" frameID="1254" frameName="adjectival"><layer name="target"><label ID="1" name="Target" start="0" end="9"/></layer></annotationSet></sentence><sentence ID="14860"><text>Adjectives sometimes precede and sometimes follow the noun they qualify .</text><annotationSet ID="26570" luID="28375" luName="adjective.n" frameID="1254" frameName="adjectival"><layer name="target"><label ID="1" name="Target" start="0" end="9"/></layer></annotationSet><annotationSet ID="26571" luID="28379" luName="noun.n" frameID="1255" frameName="noun"><layer name="target"><label ID="1" name="Target" start="54" end="57"/></layer></annotationSet><annotationSet ID="34617" luID="28437" luName="precede.v" frameID="1271" frameName="frm_sequence"><layer name="fe"><label ID="11730" name="fe_Entity_1" start="0" end="9"/><label ID="11736" name="fe_Frequency" start="11" end="19"/><label ID="11733" name="fe_Order" start="21" end="27"/><label ID="11731" name="fe_Entity_2" start="50" end="70"/></layer><layer name="target"><label ID="1" name="Target" start="21" end="27"/></layer></annotationSet><annotationSet ID="34618" luID="28436" luName="follow.v" frameID="1271" frameName="frm_sequence"><layer name="fe"><label ID="11730" name="fe_Entity_1" start="0" end="9"/><label ID="11736" name="fe_Frequency" start="33" end="41"/><label ID="11733" name="fe_Order" start="43" end="48"/><label ID="11731" name="fe_Entity_2" start="50" end="70"/></layer><layer name="target"><label ID="1" name="Target" start="43" end="48"/></layer></annotationSet></sentence><sentence ID="14861"><text>They very commonly end in pā or bā ; thus , jhyā-bā , good ; kām-bā , bitter ; le-pā , hot ; min-bā , ripe ; no-bā , tall ; reng-bā , green ; sim-bā , cold ; tum-bā , short .</text></sentence><sentence ID="14862"><text>There are , however , also other suffixes in use ; thus , ā-khām-na , unable ; kyāng-no , all ; thā-cho , straight ; kok-teng , crooked ; mlāngai , black ; tāra , white ; bāla , red .</text><annotationSet ID="26572" luID="28389" luName="suffix.n" frameID="1258" frameName="affix"><layer name="target"><label ID="1" name="Target" start="33" end="40"/></layer></annotationSet></sentence><sentence ID="14863"><text>The particle of comparison is given as oisi ; thus , the-lā ā-le the-lā ā-ngā oisi no-bā mu-lā , his brother is taller than his sister .</text><annotationSet ID="26573" luID="28315" luName="particle.n" frameID="1235" frameName="particle"><layer name="fe"><label ID="11541" name="subclass" start="13" end="25"/><label ID="11542" name="data" start="39" end="42"/></layer><layer name="target"><label ID="1" name="Target" start="4" end="11"/></layer></annotationSet></sentence><sentence ID="14864"><text>It is , however , possible that the initial o in oi-si is a miswriting for w ; compare Purik vasang .</text></sentence><sentence ID="14865"><text>Numerals .</text><annotationSet ID="28734" luID="28306" luName="numeral.n" frameID="1232" frameName="numeral"><layer name="target"><label ID="1" name="Target" start="0" end="7"/></layer></annotationSet></sentence><sentence ID="14866"><text>The first numerals are given in the list of words .</text><annotationSet ID="26574" luID="28306" luName="numeral.n" frameID="1232" frameName="numeral"><layer name="target"><label ID="1" name="Target" start="10" end="17"/></layer></annotationSet></sentence><sentence ID="14867"><text>They sometimes precede and sometimes follow the noun they qualify .</text><annotationSet ID="26575" luID="28379" luName="noun.n" frameID="1255" frameName="noun"><layer name="target"><label ID="1" name="Target" start="48" end="51"/></layer></annotationSet><annotationSet ID="34641" luID="28437" luName="precede.v" frameID="1271" frameName="frm_sequence"><layer name="fe"><label ID="11730" name="fe_Entity_1" start="0" end="3"/><label ID="11736" name="fe_Frequency" start="5" end="13"/><label ID="11731" name="fe_Entity_2" start="44" end="64"/><label ID="11733" name="fe_Order" start="15" end="21"/></layer><layer name="target"><label ID="1" name="Target" start="15" end="21"/></layer></annotationSet><annotationSet ID="34642" luID="28436" luName="follow.v" frameID="1271" frameName="frm_sequence"><layer name="fe"><label ID="11730" name="fe_Entity_1" start="0" end="3"/><label ID="11736" name="fe_Frequency" start="27" end="35"/><label ID="11733" name="fe_Order" start="37" end="42"/><label ID="11731" name="fe_Entity_2" start="44" end="64"/></layer><layer name="target"><label ID="1" name="Target" start="37" end="42"/></layer></annotationSet></sentence><sentence ID="14868"><text>Instead of ki , gi , one , the texts received from Darjeeling give gik and jik .</text></sentence><sentence ID="14869"><text>The form nhi , two , has been taken from the same source .</text></sentence><sentence ID="14870"><text>In other cases where two different forms are given in the list , the last one has been taken from a list of numerals added at the end of the version of the Parable received from the Nepal Darbar .</text></sentence><sentence ID="14871"><text>That latter source also gives forms such as chũ-gri , eleven ; chũ-ngi , twelve ; chũ-som , thirteen ; chũ-pli , fourteen ; chũ-ngā , fifteen ; chũ-ṭu , sixteen ; chũ-nis , seventeen ; chwābre , eighteen ; chu-rku , nineteen .</text></sentence><sentence ID="14872"><text>The higher numbers are counted in twenties .</text><annotationSet ID="26576" luID="28322" luName="number.n" frameID="1239" frameName="number_property"><layer name="fe"><label ID="11553" name="subclass" start="4" end="9"/><label ID="11554" name="data" start="23" end="41"/></layer><layer name="target"><label ID="1" name="Target" start="11" end="17"/></layer></annotationSet></sentence><sentence ID="14873"><text>The list of numerals just mentioned , however , gives ngi-seb , twenty ; som-seb , thirty ; pli-seb , forty ; ngā-seb , fifty ; ṭu-seb , sixty ; nis-seb , seventy ; bre-seb , eighty ; ku-seb , ninety ; chiu-seb , hundred .</text><annotationSet ID="26577" luID="28306" luName="numeral.n" frameID="1232" frameName="numeral"><layer name="fe"><label ID="11527" name="data_translation" start="137" end="141"/><label ID="11529" name="data" start="145" end="151"/><label ID="11529" name="data" start="54" end="60"/><label ID="11527" name="data_translation" start="155" end="161"/><label ID="11527" name="data_translation" start="64" end="69"/><label ID="11529" name="data" start="165" end="171"/><label ID="11529" name="data" start="73" end="79"/><label ID="11527" name="data_translation" start="175" end="180"/><label ID="11527" name="data_translation" start="83" end="88"/><label ID="11529" name="data" start="184" end="189"/><label ID="11529" name="data" start="92" end="98"/><label ID="11527" name="data_translation" start="193" end="198"/><label ID="11527" name="data_translation" start="102" end="106"/><label ID="11529" name="data" start="202" end="209"/><label ID="11529" name="data" start="110" end="116"/><label ID="11527" name="data_translation" start="213" end="219"/><label ID="11527" name="data_translation" start="120" end="124"/><label ID="11529" name="data" start="128" end="133"/></layer><layer name="target"><label ID="1" name="Target" start="12" end="19"/></layer></annotationSet></sentence><sentence ID="14874"><text>Chui and chiu , ten , point to the pronunciation chü .</text></sentence><sentence ID="14875"><text>Pronouns .</text><annotationSet ID="28735" luID="28334" luName="pronoun.n" frameID="1243" frameName="pronominal"><layer name="target"><label ID="1" name="Target" start="0" end="7"/></layer></annotationSet></sentence><sentence ID="14876"><text>Pronouns are inflected like nouns .</text><annotationSet ID="26578" luID="28334" luName="pronoun.n" frameID="1243" frameName="pronominal"><layer name="target"><label ID="1" name="Target" start="0" end="7"/></layer></annotationSet><annotationSet ID="26580" luID="28379" luName="noun.n" frameID="1255" frameName="noun"><layer name="target"><label ID="1" name="Target" start="28" end="32"/></layer></annotationSet></sentence><sentence ID="14877"><text>The principal forms of the personal pronouns will be seen from the table which follows .</text><annotationSet ID="26589" luID="28334" luName="pronoun.n" frameID="1243" frameName="pronominal"><layer name="fe"><label ID="11591" name="sublass" start="27" end="34"/></layer><layer name="target"><label ID="1" name="Target" start="36" end="43"/></layer></annotationSet></sentence><sentence ID="14878"><text>Forms such as yeni kāte , you ; theni-kāte-se , by them , and so forth , of course also occur .</text></sentence><sentence ID="14879"><text>Forms such as hoju , he ; hot-lā , his ; hochhe , by him , have been recorded from Darjeeling .</text></sentence><sentence ID="14880"><text>Demonstrative pronouns are chu , this ; the , u-chu , ho-ju , ho-jā , that .</text><annotationSet ID="26593" luID="28334" luName="pronoun.n" frameID="1243" frameName="pronominal"><layer name="fe"><label ID="11591" name="sublass" start="0" end="12"/><label ID="11589" name="data" start="27" end="29"/><label ID="11590" name="data_translation" start="33" end="36"/><label ID="11589" name="data" start="46" end="50"/><label ID="11589" name="data" start="54" end="58"/><label ID="11589" name="data" start="62" end="66"/><label ID="11590" name="data_translation" start="70" end="73"/></layer><layer name="target"><label ID="1" name="Target" start="14" end="21"/></layer></annotationSet></sentence><sentence ID="14881"><text>Interrogative pronouns are khā and hālā , who ?</text><annotationSet ID="26594" luID="28334" luName="pronoun.n" frameID="1243" frameName="pronominal"><layer name="fe"><label ID="11591" name="sublass" start="0" end="12"/><label ID="11589" name="data" start="27" end="29"/><label ID="11589" name="data" start="35" end="38"/><label ID="11590" name="data_translation" start="42" end="44"/></layer><layer name="target"><label ID="1" name="Target" start="14" end="21"/></layer></annotationSet></sentence><sentence ID="14882"><text>tigā , tikā , and ki , what ?</text></sentence><sentence ID="14883"><text>kāde , how many ?</text></sentence><sentence ID="14884"><text>and so forth .</text></sentence><sentence ID="14885"><text>By adding the indefinite particle nu or no indefinite pronouns are effected ; thus , khāl-che-nu , by anyone ; tiki-no , anything ; khāi-mā-ye-no , ever .</text><annotationSet ID="26595" luID="28315" luName="particle.n" frameID="1235" frameName="particle"><layer name="fe"><label ID="11541" name="subclass" start="14" end="23"/><label ID="11542" name="data" start="34" end="35"/><label ID="11542" name="data" start="40" end="41"/></layer><layer name="target"><label ID="1" name="Target" start="25" end="32"/></layer></annotationSet><annotationSet ID="26596" luID="28334" luName="pronoun.n" frameID="1243" frameName="pronominal"><layer name="fe"><label ID="11591" name="sublass" start="43" end="52"/></layer><layer name="target"><label ID="1" name="Target" start="54" end="61"/></layer></annotationSet></sentence><sentence ID="14886"><text>Note also the reflexive pronoun rāng-lā or rhāng-lā , own .</text><annotationSet ID="26597" luID="28334" luName="pronoun.n" frameID="1243" frameName="pronominal"><layer name="fe"><label ID="11591" name="sublass" start="14" end="22"/><label ID="11589" name="data" start="32" end="38"/><label ID="11589" name="data" start="43" end="50"/><label ID="11590" name="data_translation" start="54" end="56"/></layer><layer name="target"><label ID="1" name="Target" start="24" end="30"/></layer></annotationSet></sentence><sentence ID="14887"><text>Verbs .</text><annotationSet ID="28736" luID="28337" luName="verb.n" frameID="1244" frameName="verbal"><layer name="target"><label ID="1" name="Target" start="0" end="4"/></layer></annotationSet></sentence><sentence ID="14888"><text>The verb is still virtually a noun .</text><annotationSet ID="26598" luID="28337" luName="verb.n" frameID="1244" frameName="verbal"><layer name="target"><label ID="1" name="Target" start="4" end="7"/></layer></annotationSet><annotationSet ID="26599" luID="28379" luName="noun.n" frameID="1255" frameName="noun"><layer name="target"><label ID="1" name="Target" start="30" end="33"/></layer></annotationSet></sentence><sentence ID="14889"><text>The list of words gives forms such as ni-n , goest , where the final n seems to be a pronominal suffix of the second person .</text></sentence><sentence ID="14890"><text>The suffix m in forms such as pin-ji-m , he gave , in the Darjeeling specimens , is perhaps a corresponding suffix of the third person .</text><annotationSet ID="26648" luID="28389" luName="suffix.n" frameID="1258" frameName="affix"><layer name="fe"><label ID="11678" name="data" start="11" end="11"/><label ID="11679" name="language_variety" start="58" end="67"/></layer><layer name="target"><label ID="1" name="Target" start="4" end="9"/></layer></annotationSet><annotationSet ID="28756" luID="28389" luName="suffix.n" frameID="1258" frameName="affix"><layer name="target"><label ID="1" name="Target" start="108" end="113"/></layer></annotationSet><annotationSet ID="28757" luID="28299" luName="person.n" frameID="1229" frameName="person_property"><layer name="fe"><label ID="11512" name="subclass" start="122" end="126"/></layer><layer name="target"><label ID="1" name="Target" start="128" end="133"/></layer></annotationSet></sentence><sentence ID="14891"><text>It is , however , more probable that this m is simply the verb substantive .</text><annotationSet ID="26649" luID="28337" luName="verb.n" frameID="1244" frameName="verbal"><layer name="fe"><label ID="11594" name="data" start="42" end="42"/></layer><layer name="target"><label ID="1" name="Target" start="58" end="61"/></layer></annotationSet></sentence><sentence ID="14892"><text>The use of pronominal suffixes is , at all events , no regular feature of Murmi , though it is possible that there is a tendency to distinguish the various persons of the verb .</text><annotationSet ID="26650" luID="28389" luName="suffix.n" frameID="1258" frameName="affix"><layer name="fe"><label ID="11677" name="subclass" start="11" end="20"/><label ID="11679" name="language_variety" start="74" end="78"/></layer><layer name="target"><label ID="1" name="Target" start="22" end="29"/></layer></annotationSet><annotationSet ID="26651" luID="28337" luName="verb.n" frameID="1244" frameName="verbal"><layer name="fe"><label ID="11593" name="language_variety" start="74" end="78"/></layer><layer name="target"><label ID="1" name="Target" start="171" end="174"/></layer></annotationSet><annotationSet ID="26652" luID="28299" luName="person.n" frameID="1229" frameName="person_property"><layer name="fe"><label ID="11512" name="subclass" start="164" end="174"/><label ID="11513" name="language_variety" start="74" end="78"/></layer><layer name="target"><label ID="1" name="Target" start="156" end="162"/></layer></annotationSet></sentence><sentence ID="14893"><text>Such a tendency is observable in several connected dialects .</text></sentence><sentence ID="14894"><text>It is also possible to suggest the influence of other dialects in which the use of personal suffixes is quite regular .</text><annotationSet ID="26653" luID="28389" luName="suffix.n" frameID="1258" frameName="affix"><layer name="fe"><label ID="11677" name="subclass" start="83" end="90"/></layer><layer name="target"><label ID="1" name="Target" start="92" end="99"/></layer></annotationSet></sentence><sentence ID="14895"><text>Verb substantive .</text><annotationSet ID="26654" luID="28337" luName="verb.n" frameID="1244" frameName="verbal"><layer name="target"><label ID="1" name="Target" start="0" end="3"/></layer></annotationSet></sentence><sentence ID="14896"><text>The usual base of the verb substantive is mu , present mu-lā , past mu-bā .</text><annotationSet ID="26655" luID="28337" luName="verb.n" frameID="1244" frameName="verbal"><layer name="fe"><label ID="11596" name="subclass" start="27" end="37"/></layer><layer name="target"><label ID="1" name="Target" start="22" end="25"/></layer></annotationSet><annotationSet ID="28758" luID="28303" luName="base.n" frameID="1231" frameName="morpheme"><layer name="fe"><label ID="11524" name="data" start="42" end="43"/></layer><layer name="target"><label ID="1" name="Target" start="10" end="13"/></layer></annotationSet></sentence><sentence ID="14897"><text>Other forms are supplied from other bases such as tā , to become ; re , to stand .</text><annotationSet ID="28759" luID="28303" luName="base.n" frameID="1231" frameName="morpheme"><layer name="fe"><label ID="11524" name="data" start="50" end="51"/><label ID="11522" name="data_translation" start="55" end="63"/><label ID="11524" name="data" start="67" end="68"/><label ID="11522" name="data_translation" start="72" end="79"/></layer><layer name="target"><label ID="1" name="Target" start="36" end="40"/></layer></annotationSet></sentence><sentence ID="14898"><text>In the ki ni , that what is ?</text></sentence><sentence ID="14899"><text>we have a base ni .</text><annotationSet ID="28760" luID="28303" luName="base.n" frameID="1231" frameName="morpheme"><layer name="fe"><label ID="11524" name="data" start="15" end="16"/></layer><layer name="target"><label ID="1" name="Target" start="10" end="13"/></layer></annotationSet></sentence><sentence ID="14900"><text>Another base ke apparently occurs in ye-lā-ke , it is thine .</text><annotationSet ID="26656" luID="28303" luName="base.n" frameID="1231" frameName="morpheme"><layer name="fe"><label ID="11524" name="data" start="13" end="14"/></layer><layer name="target"><label ID="1" name="Target" start="8" end="11"/></layer></annotationSet></sentence><sentence ID="14901"><text>Finite verbs .</text><annotationSet ID="28761" luID="28337" luName="verb.n" frameID="1244" frameName="verbal"><layer name="fe"><label ID="11596" name="subclass" start="0" end="5"/></layer><layer name="target"><label ID="1" name="Target" start="7" end="11"/></layer></annotationSet></sentence><sentence ID="14902"><text>The verb substantive is freely used in the formation of the tenses of finite verbs .</text><annotationSet ID="26691" luID="28337" luName="verb.n" frameID="1244" frameName="verbal"><layer name="fe"><label ID="11596" name="subclass" start="70" end="75"/></layer><layer name="target"><label ID="1" name="Target" start="77" end="81"/></layer></annotationSet><annotationSet ID="28762" luID="28388" luName="tense.n" frameID="1257" frameName="tense_property"><layer name="target"><label ID="1" name="Target" start="60" end="65"/></layer></annotationSet><annotationSet ID="28763" luID="28337" luName="verb.n" frameID="1244" frameName="verbal"><layer name="target"><label ID="1" name="Target" start="4" end="7"/></layer></annotationSet></sentence><sentence ID="14903"><text>Present time .</text><annotationSet ID="28764" luID="28385" luName="present.n" frameID="1257" frameName="tense_property"><layer name="target"><label ID="1" name="Target" start="0" end="6"/></layer></annotationSet></sentence><sentence ID="14904"><text>The base alone is sometimes used as a present tense .</text><annotationSet ID="26865" luID="28303" luName="base.n" frameID="1231" frameName="morpheme"><layer name="target"><label ID="1" name="Target" start="4" end="7"/></layer></annotationSet><annotationSet ID="26866" luID="28388" luName="tense.n" frameID="1257" frameName="tense_property"><layer name="fe"><label ID="11672" name="subclass" start="38" end="44"/></layer><layer name="target"><label ID="1" name="Target" start="46" end="50"/></layer></annotationSet><annotationSet ID="34643" luID="28448" luName="use.v" frameID="1274" frameName="frm_using"><layer name="fe"><label ID="11745" name="fe_Entity" start="0" end="13"/><label ID="11746" name="fe_Role" start="33" end="50"/></layer><layer name="target"><label ID="1" name="Target" start="28" end="31"/></layer></annotationSet></sentence><sentence ID="14905"><text>Thus , ye-ni mu , we go .</text></sentence><sentence ID="14906"><text>The most common suffix of the present is apparently lā ; thus , mu-lā , am ; rop-lā , strike .</text><annotationSet ID="26867" luID="28389" luName="suffix.n" frameID="1258" frameName="affix"><layer name="fe"><label ID="11678" name="data" start="52" end="53"/></layer><layer name="target"><label ID="1" name="Target" start="16" end="21"/></layer></annotationSet><annotationSet ID="28765" luID="28385" luName="present.n" frameID="1257" frameName="tense_property"><layer name="target"><label ID="1" name="Target" start="30" end="36"/></layer></annotationSet></sentence><sentence ID="14907"><text>The suffix pā or bā in forms such as the-se rop-pā , he strikes ; chhā-se chi-bā , having grazed sits , he is grazing , corresponds to Tibetan pa or ba and does not contain any special notion of time .</text><annotationSet ID="26868" luID="28389" luName="suffix.n" frameID="1258" frameName="affix"><layer name="fe"><label ID="11678" name="data" start="11" end="12"/><label ID="11678" name="data" start="17" end="18"/><label ID="11679" name="language_variety" start="135" end="141"/></layer><layer name="target"><label ID="1" name="Target" start="4" end="9"/></layer></annotationSet></sentence><sentence ID="14908"><text>Forms such as si-la-ji , I die ; ha-ji , he comes ; rop-chi , thou strikest ; ngā-ni ni-sai , we go , and so forth , apparently contain the same suffix as that which is generally used with the meaning of a past .</text><annotationSet ID="26869" luID="28389" luName="suffix.n" frameID="1258" frameName="affix"><layer name="target"><label ID="1" name="Target" start="145" end="150"/></layer></annotationSet></sentence><sentence ID="14909"><text>A similar use of the suffix of past time is not uncommon in connected forms of speech .</text><annotationSet ID="26870" luID="28389" luName="suffix.n" frameID="1258" frameName="affix"><layer name="target"><label ID="1" name="Target" start="21" end="26"/></layer></annotationSet><annotationSet ID="26871" luID="28358" luName="speech.n" frameID="1249" frameName="linguistic_system"><layer name="target"><label ID="1" name="Target" start="79" end="84"/></layer></annotationSet></sentence><sentence ID="14910"><text>It is perhaps due to the intention of the speaker to represent the action of the verb as an established fact .</text><annotationSet ID="26872" luID="28337" luName="verb.n" frameID="1244" frameName="verbal"><layer name="target"><label ID="1" name="Target" start="81" end="84"/></layer></annotationSet></sentence><sentence ID="14911"><text>Past time .</text><annotationSet ID="28766" luID="28384" luName="past.n" frameID="1257" frameName="tense_property"><layer name="target"><label ID="1" name="Target" start="0" end="3"/></layer></annotationSet></sentence><sentence ID="14912"><text>The usual suffix of past time is ji as in Gurung ; thus , pān-ji , he said ; ni-ji , he went .</text><annotationSet ID="26873" luID="28389" luName="suffix.n" frameID="1258" frameName="affix"><layer name="fe"><label ID="11677" name="subclass" start="17" end="28"/><label ID="11678" name="data" start="33" end="34"/><label ID="11679" name="language_variety" start="42" end="47"/></layer><layer name="target"><label ID="1" name="Target" start="10" end="15"/></layer></annotationSet><annotationSet ID="26874" luID="28384" luName="past.n" frameID="1257" frameName="tense_property"><layer name="target"><label ID="1" name="Target" start="20" end="23"/></layer></annotationSet></sentence><sentence ID="14913"><text>Instead of ji we sometimes find chi ; thus , rop-chi , I have beaten .</text></sentence><sentence ID="14914"><text>Chi is perhaps the correct form after hard consonants .</text><annotationSet ID="26875" luID="28282" luName="consonant.n" frameID="1225" frameName="form_unit"><layer name="fe"><label ID="11494" name="subclass" start="38" end="41"/><label ID="11496" name="data" start="0" end="2"/></layer><layer name="target"><label ID="1" name="Target" start="43" end="52"/></layer></annotationSet></sentence><sentence ID="14915"><text>An m is sometimes added in the specimens received from Darjeeling .</text></sentence><sentence ID="14916"><text>Thus , ngyok-chhi-m , he asked ; pin-ji-m , he gave .</text></sentence><sentence ID="14917"><text>Such forms are apparently only used in the third person .</text><annotationSet ID="26876" luID="28299" luName="person.n" frameID="1229" frameName="person_property"><layer name="fe"><label ID="11512" name="subclass" start="43" end="47"/></layer><layer name="target"><label ID="1" name="Target" start="49" end="54"/></layer></annotationSet></sentence><sentence ID="14918"><text>Forms such as rop , struck ; pāng-bā , said ; khu-bā , boughtest , and so on , are indefinite with regard to time .</text></sentence><sentence ID="14919"><text>Ngae rop chi jin-ji , I had beaten , perhaps means ‘ I struck finished ’ .</text></sentence><sentence ID="14920"><text>Future .</text></sentence><sentence ID="14921"><text>The present suffix lā is also used with the meaning of a future ; thus , pāng-lā , I shall say .</text><annotationSet ID="26877" luID="28389" luName="suffix.n" frameID="1258" frameName="affix"><layer name="fe"><label ID="11677" name="subclass" start="4" end="10"/><label ID="11678" name="data" start="19" end="20"/></layer><layer name="target"><label ID="1" name="Target" start="12" end="17"/></layer></annotationSet></sentence><sentence ID="14922"><text>Forms such as majā-laī , let us make merry , are perhaps imperative .</text><annotationSet ID="26878" luID="28407" luName="imperative.n" frameID="1265" frameName="mood_property"><layer name="fe"><label ID="11705" name="data" start="14" end="21"/><label ID="11706" name="data_translation" start="25" end="41"/></layer><layer name="target"><label ID="1" name="Target" start="57" end="66"/></layer></annotationSet></sentence><sentence ID="14923"><text>Imperative .</text><annotationSet ID="26879" luID="28407" luName="imperative.n" frameID="1265" frameName="mood_property"><layer name="target"><label ID="1" name="Target" start="0" end="9"/></layer></annotationSet></sentence><sentence ID="14924"><text>The usual suffixes of the imperative are u or o and go ; thus , chā-u , eat ; re-go , stand ; rob-ko , beat .</text><annotationSet ID="26880" luID="28389" luName="suffix.n" frameID="1258" frameName="affix"><layer name="fe"><label ID="11677" name="subclass" start="19" end="35"/><label ID="11678" name="data" start="41" end="41"/><label ID="11678" name="data" start="46" end="46"/><label ID="11725" name="fe_Data_Translation" start="52" end="53"/></layer><layer name="target"><label ID="1" name="Target" start="10" end="17"/></layer></annotationSet><annotationSet ID="26881" luID="28407" luName="imperative.n" frameID="1265" frameName="mood_property"><layer name="target"><label ID="1" name="Target" start="26" end="35"/></layer></annotationSet></sentence><sentence ID="14925"><text>Other sources also give imperatives such as rob , beat ; yar , run , and so forth , where no suffix is added .</text><annotationSet ID="26882" luID="28407" luName="imperative.n" frameID="1265" frameName="mood_property"><layer name="fe"><label ID="11705" name="data" start="44" end="46"/><label ID="11706" name="data_translation" start="50" end="53"/><label ID="11705" name="data" start="57" end="59"/><label ID="11706" name="data_translation" start="63" end="65"/></layer><layer name="target"><label ID="1" name="Target" start="24" end="34"/></layer></annotationSet><annotationSet ID="28767" luID="28389" luName="suffix.n" frameID="1258" frameName="affix"><layer name="target"><label ID="1" name="Target" start="93" end="98"/></layer></annotationSet></sentence><sentence ID="14926"><text>The form laī , let us make , has already been mentioned .</text></sentence><sentence ID="14927"><text>Verbal nouns and participles .</text><annotationSet ID="26883" luID="28379" luName="noun.n" frameID="1255" frameName="noun"><layer name="fe"><label ID="11661" name="subclass" start="0" end="5"/></layer><layer name="target"><label ID="1" name="Target" start="7" end="11"/></layer></annotationSet></sentence><sentence ID="14928"><text>The usual verbal noun ends in bā ; thus , chhā-bā , to graze ; khā-bā-se , by his coming , because he came ; khā-bā-chhyām , coming-with , when he came ; mrin-bā-ri , filling to , to fill .</text><annotationSet ID="27050" luID="28379" luName="noun.n" frameID="1255" frameName="noun"><layer name="fe"><label ID="11661" name="subclass" start="10" end="15"/><label ID="11659" name="data" start="30" end="31"/></layer><layer name="target"><label ID="1" name="Target" start="17" end="20"/></layer></annotationSet></sentence><sentence ID="14929"><text>It will be seen that postpositions can be added to such forms .</text></sentence><sentence ID="14930"><text>The base alone is also used as a verbal noun ; thus , chā ā-khām-na , to-eat unable .</text><annotationSet ID="27051" luID="28379" luName="noun.n" frameID="1255" frameName="noun"><layer name="fe"><label ID="11661" name="subclass" start="33" end="38"/></layer><layer name="target"><label ID="1" name="Target" start="40" end="43"/></layer></annotationSet><annotationSet ID="27052" luID="28303" luName="base.n" frameID="1231" frameName="morpheme"><layer name="target"><label ID="1" name="Target" start="4" end="7"/></layer></annotationSet><annotationSet ID="34644" luID="28448" luName="use.v" frameID="1274" frameName="frm_using"><layer name="fe"><label ID="11745" name="fe_Entity" start="0" end="13"/><label ID="11746" name="fe_Role" start="28" end="43"/></layer><layer name="target"><label ID="1" name="Target" start="23" end="26"/></layer></annotationSet></sentence><sentence ID="14931"><text>Other verbal nouns are formed by adding lā , nu , sam , and si ; thus , tā-lā , to be ; tā-sam ( Darjeeling ) , to be ; lā-nu ( Darjeeling ) , to make ; lā-si , to make .</text><annotationSet ID="27053" luID="28379" luName="noun.n" frameID="1255" frameName="noun"><layer name="fe"><label ID="11661" name="subclass" start="6" end="11"/></layer><layer name="target"><label ID="1" name="Target" start="13" end="17"/></layer></annotationSet><annotationSet ID="28768" luID="28381" luName="form.v" frameID="1256" frameName="formation"><layer name="fe"><label ID="11662" name="formed_entity" start="6" end="17"/><label ID="11664" name="process" start="30" end="38"/><label ID="11669" name="data" start="40" end="41"/><label ID="11669" name="data" start="45" end="46"/><label ID="11669" name="data" start="50" end="52"/><label ID="11669" name="data" start="60" end="61"/></layer><layer name="target"><label ID="1" name="Target" start="23" end="28"/></layer></annotationSet></sentence><sentence ID="14932"><text>Tā-lā , to be , is perhaps a genitive .</text><annotationSet ID="27054" luID="28411" luName="genitive.n" frameID="1266" frameName="case_property"><layer name="fe"><label ID="11708" name="data" start="0" end="4"/><label ID="11709" name="data_translation" start="8" end="12"/></layer><layer name="target"><label ID="1" name="Target" start="29" end="36"/></layer></annotationSet></sentence><sentence ID="14933"><text>Compare ngāī yāng-lā ansa-bhāg , me-by getting-of share , the share which I shall get .</text></sentence><sentence ID="14934"><text>Forms such as tā-lā jhin-ji , having been , perhaps contain the same suffix and a postposition jhin-ji , finishing , from , after .</text><annotationSet ID="27055" luID="28389" luName="suffix.n" frameID="1258" frameName="affix"><layer name="fe"><label ID="11678" name="data" start="95" end="101"/></layer><layer name="target"><label ID="1" name="Target" start="69" end="74"/></layer></annotationSet><annotationSet ID="27056" luID="28373" luName="postposition.n" frameID="1253" frameName="adposition"><layer name="fe"><label ID="11652" name="data" start="95" end="101"/></layer><layer name="target"><label ID="1" name="Target" start="82" end="93"/></layer></annotationSet></sentence><sentence ID="14935"><text>Compare , however , the suffix lā of the present and future .</text><annotationSet ID="27057" luID="28389" luName="suffix.n" frameID="1258" frameName="affix"><layer name="fe"><label ID="11678" name="data" start="31" end="32"/></layer><layer name="target"><label ID="1" name="Target" start="24" end="29"/></layer></annotationSet><annotationSet ID="28769" luID="28385" luName="present.n" frameID="1257" frameName="tense_property"><layer name="target"><label ID="1" name="Target" start="41" end="47"/></layer></annotationSet><annotationSet ID="28770" luID="28386" luName="future.n" frameID="1257" frameName="tense_property"><layer name="target"><label ID="1" name="Target" start="53" end="58"/></layer></annotationSet></sentence><sentence ID="14936"><text>The form ending in bā is also used as a relative participle ; thus , ḍarmā-ri ṭi-bā chākara-dugu , wages-in living servants , hired servants .</text><annotationSet ID="34645" luID="28448" luName="use.v" frameID="1274" frameName="frm_using"><layer name="fe"><label ID="11745" name="fe_Entity" start="0" end="20"/><label ID="11746" name="fe_Role" start="35" end="58"/></layer><layer name="target"><label ID="1" name="Target" start="30" end="33"/></layer></annotationSet></sentence><sentence ID="14937"><text>Another suffix used to form relative participles is nā ; thus , yennā sampati chā-si pin-nā chu yennā kolā , your property having-eaten giving this your son ; this your son who wasted your property .</text><annotationSet ID="27058" luID="28347" luName="suffix.v" frameID="1246" frameName="affixation"><layer name="fe"><label ID="11613" name="result" start="28" end="47"/><label ID="11602" name="affix" start="52" end="53"/></layer><layer name="target"><label ID="1" name="Target" start="8" end="13"/></layer></annotationSet><annotationSet ID="27059" luID="28381" luName="form.v" frameID="1256" frameName="formation"><layer name="fe"><label ID="11662" name="formed_entity" start="28" end="47"/><label ID="11669" name="data" start="52" end="53"/></layer><layer name="target"><label ID="1" name="Target" start="23" end="26"/></layer></annotationSet></sentence><sentence ID="14938"><text>The suffix nā is also used to form a kind of adverbial participle .</text><annotationSet ID="27060" luID="28389" luName="suffix.n" frameID="1258" frameName="affix"><layer name="fe"><label ID="11678" name="data" start="11" end="12"/></layer><layer name="target"><label ID="1" name="Target" start="4" end="9"/></layer></annotationSet><annotationSet ID="27061" luID="28381" luName="form.v" frameID="1256" frameName="formation"><layer name="fe"><label ID="11663" name="formed_from" start="4" end="9"/><label ID="11663" name="formed_from" start="11" end="12"/><label ID="11662" name="formed_entity" start="45" end="64"/><label ID="11663" name="formed_from" start="0" end="3"/><label ID="11663" name="formed_from" start="10" end="10"/><label ID="11662" name="formed_entity" start="35" end="44"/></layer><layer name="target"><label ID="1" name="Target" start="30" end="33"/></layer></annotationSet></sentence><sentence ID="14939"><text>Thus , kathā the-nā lām-bā , tale delivering sat , he sat delivering a tale ; ti-ki ā-tā-nā , anything not befalling , without any misfortune .</text></sentence><sentence ID="14940"><text>Other adverbial participles are formed from the various verbal nouns by adding postpositions ; thus , pāng-mā , saying in , while saying ; pāng-min , while saying ; bi-se , by saying , if you say .</text><annotationSet ID="27062" luID="28379" luName="noun.n" frameID="1255" frameName="noun"><layer name="fe"><label ID="11661" name="subclass" start="56" end="61"/></layer><layer name="target"><label ID="1" name="Target" start="63" end="67"/></layer></annotationSet><annotationSet ID="28771" luID="28381" luName="form.v" frameID="1256" frameName="formation"><layer name="fe"><label ID="11662" name="formed_entity" start="6" end="26"/><label ID="11663" name="formed_from" start="56" end="67"/><label ID="11664" name="process" start="69" end="91"/></layer><layer name="target"><label ID="1" name="Target" start="32" end="37"/></layer></annotationSet></sentence><sentence ID="14941"><text>Forms such as si-bāng , dead ; mā-bāng , lost , probably contain the suffix bā mentioned in the preceding .</text><annotationSet ID="27063" luID="28389" luName="suffix.n" frameID="1258" frameName="affix"><layer name="fe"><label ID="11678" name="data" start="76" end="77"/></layer><layer name="target"><label ID="1" name="Target" start="69" end="74"/></layer></annotationSet></sentence><sentence ID="14942"><text>Compare also tā-si chi-bā , having-become sitting , being ; rop-si chi-bā , having-struck sitting , striking .</text></sentence><sentence ID="14943"><text>The usual conjunctive participle ends in si , se , or chhi ; thus , pāng-si , having said ; kwān-chhi , having put on .</text></sentence><sentence ID="14944"><text>A particle nā or nām is sometimes added ; thus , rup-si-nā , gathering ; khā-ji-nām , coming , in the Darjeeling specimens .</text><annotationSet ID="27064" luID="28315" luName="particle.n" frameID="1235" frameName="particle"><layer name="fe"><label ID="11542" name="data" start="11" end="12"/><label ID="11542" name="data" start="17" end="19"/><label ID="11540" name="language_variety" start="102" end="111"/></layer><layer name="target"><label ID="1" name="Target" start="2" end="9"/></layer></annotationSet></sentence><sentence ID="14945"><text>The same sources also exhibit forms such as bi-sam and bi-sang , saying ; ngyo-chhi-mam , calling , and so forth .</text></sentence><sentence ID="14946"><text>Passive voice .</text><annotationSet ID="27065" luID="28292" luName="voice.n" frameID="1227" frameName="voice_property"><layer name="fe"><label ID="11507" name="subclass" start="0" end="6"/></layer><layer name="target"><label ID="1" name="Target" start="8" end="12"/></layer></annotationSet></sentence><sentence ID="14947"><text>There is no passive voice .</text><annotationSet ID="27066" luID="28292" luName="voice.n" frameID="1227" frameName="voice_property"><layer name="fe"><label ID="11507" name="subclass" start="12" end="18"/></layer><layer name="target"><label ID="1" name="Target" start="20" end="24"/></layer></annotationSet></sentence><sentence ID="14948"><text>Ngā-tā rop-ji , I am struck , literally means ‘ me struck ’ .</text></sentence><sentence ID="14949"><text>The ka in ngā-tā rop-ka-lā , I shall be beaten , does not seem to add anything to the meaning .</text></sentence><sentence ID="14950"><text>It is perhaps a verb substantive .</text><annotationSet ID="27067" luID="28337" luName="verb.n" frameID="1244" frameName="verbal"><layer name="target"><label ID="1" name="Target" start="16" end="19"/></layer></annotationSet></sentence><sentence ID="14951"><text>Compare also ṭi-si-ka-na , living .</text></sentence><sentence ID="14952"><text>Causative .</text></sentence><sentence ID="14953"><text>There is only one certain instance of a causative in the specimens , viż , chhā-bā , to graze .</text></sentence><sentence ID="14954"><text>It is formed from chā-bā , to eat , by aspirating the initial consonant .</text><annotationSet ID="27068" luID="28381" luName="form.v" frameID="1256" frameName="formation"><layer name="fe"><label ID="11669" name="data" start="18" end="23"/><label ID="11670" name="data_translation" start="27" end="32"/><label ID="11664" name="process" start="36" end="70"/></layer><layer name="target"><label ID="1" name="Target" start="6" end="11"/></layer></annotationSet><annotationSet ID="27069" luID="28282" luName="consonant.n" frameID="1225" frameName="form_unit"><layer name="fe"><label ID="11495" name="position" start="54" end="60"/></layer><layer name="target"><label ID="1" name="Target" start="62" end="70"/></layer></annotationSet></sentence><sentence ID="14955"><text>Negative particle .</text><annotationSet ID="27070" luID="28315" luName="particle.n" frameID="1235" frameName="particle"><layer name="fe"><label ID="11541" name="subclass" start="0" end="7"/></layer><layer name="target"><label ID="1" name="Target" start="9" end="16"/></layer></annotationSet></sentence><sentence ID="14956"><text>The negative particle is a prefixed ā , and ni or na is usually added to the base ; thus , ā-pin-ni , did not give ; ā-yo-na , did not get .</text><annotationSet ID="27071" luID="28315" luName="particle.n" frameID="1235" frameName="particle"><layer name="fe"><label ID="11541" name="subclass" start="4" end="11"/></layer><layer name="target"><label ID="1" name="Target" start="13" end="20"/></layer></annotationSet><annotationSet ID="27072" luID="28349" luName="prefixed.a" frameID="1246" frameName="affixation"><layer name="fe"><label ID="11602" name="affix" start="36" end="36"/><label ID="11602" name="affix" start="44" end="45"/><label ID="11602" name="affix" start="50" end="51"/><label ID="11601" name="stem" start="77" end="80"/><label ID="11612" name="data" start="91" end="98"/><label ID="11617" name="data_translation" start="102" end="113"/><label ID="11612" name="data" start="117" end="123"/><label ID="11617" name="data_translation" start="127" end="137"/></layer><layer name="target"><label ID="1" name="Target" start="27" end="34"/></layer></annotationSet><annotationSet ID="27073" luID="28303" luName="base.n" frameID="1231" frameName="morpheme"><layer name="target"><label ID="1" name="Target" start="77" end="80"/></layer></annotationSet></sentence><sentence ID="14957"><text>In chhyāng-do-lā , did not transgress , the negative particle must be contained in the o preceding the lā , or else chhyāng-do-lā means ‘ obeyed ’ .</text><annotationSet ID="27074" luID="28315" luName="particle.n" frameID="1235" frameName="particle"><layer name="fe"><label ID="11541" name="subclass" start="44" end="51"/><label ID="11542" name="data" start="103" end="104"/><label ID="11542" name="data" start="87" end="87"/><label ID="11542" name="data" start="116" end="128"/><label ID="11543" name="data_translation" start="138" end="143"/><label ID="11542" name="data" start="3" end="15"/><label ID="11543" name="data_translation" start="19" end="36"/></layer><layer name="target"><label ID="1" name="Target" start="53" end="60"/></layer></annotationSet></sentence><sentence ID="14958"><text>Note forms such as krā-bā ā-hin , crying was-not , I did not cry , where the negative has been prefixed to the auxiliary and not to the principal verb .</text><annotationSet ID="27075" luID="28337" luName="verb.n" frameID="1244" frameName="verbal"><layer name="fe"><label ID="11596" name="subclass" start="136" end="144"/></layer><layer name="target"><label ID="1" name="Target" start="146" end="149"/></layer></annotationSet><annotationSet ID="27076" luID="28336" luName="auxiliary.n " frameID="1244" frameName="verbal"><layer name="target"><label ID="1" name="Target" start="111" end="119"/></layer></annotationSet><annotationSet ID="27077" luID="28349" luName="prefixed.a" frameID="1246" frameName="affixation"><layer name="fe"><label ID="11602" name="affix" start="77" end="84"/><label ID="11601" name="stem" start="111" end="119"/></layer><layer name="target"><label ID="1" name="Target" start="95" end="102"/></layer></annotationSet></sentence><sentence ID="14959"><text>Order of words .</text></sentence><sentence ID="14960"><text>The usual order of words is subject , object , verb .</text><annotationSet ID="27078" luID="28337" luName="verb.n" frameID="1244" frameName="verbal"><layer name="target"><label ID="1" name="Target" start="47" end="50"/></layer></annotationSet><annotationSet ID="34646" luID="28439" luName="order.n" frameID="1271" frameName="frm_sequence"><layer name="fe"><label ID="11733" name="fe_Order" start="28" end="50"/></layer><layer name="target"><label ID="1" name="Target" start="10" end="14"/></layer></annotationSet></sentence><sentence ID="14961"><text>For further details the student is referred to the specimens which follow .</text></sentence><sentence ID="14962"><text>The first is a version of the Parable of the Prodigal Son which has been kindly forwarded from the Nepal Darbar .</text></sentence><sentence ID="14963"><text>The second is a version of a well-known popular tale which has been taken down in Darjeeling .</text></sentence><sentence ID="14964"><text>A list of Standard Words and Phrases from the Nepal Darbar will be found on pp .</text><annotationSet ID="27079" luID="28422" luName="phrase.n" frameID="1267" frameName="phrase"><layer name="target"><label ID="1" name="Target" start="29" end="35"/></layer></annotationSet></sentence><sentence ID="14965"><text>254 and ff.</text></sentence></fullTextAnnotation>
